{
  "apiVersion": "swecircuit/specialist/v1alpha1",
  "kind": "SpecialistAgentHandoff",
  "outcome": "pass",
  "destination": "codex.main",
  "goal": {
    "id": "v12.ide-run-loop.architecture",
    "revision": 1,
    "digest": "sha256:2fad6a458f7b7e8060a5967c8edc60ae7c05ffd4b5cb97512e998ea227215d2f"
  },
  "agent": {
    "id": "agent.855d25082db5af8f0d0049f54e53a11038d1ec56264f34e10e2097425f895486",
    "blueprintDigest": "sha256:fcb9a6a04f0ce2e5f524daa38ac817a5332534ce23a737ca5d66217dcd0ee06b"
  },
  "compilationDigest": "sha256:662a7ca9303d3d347dbbe32835b3f2635b37f22ef8b051214a9e5924cb3f6415",
  "summary": "A deterministic monotonic V12 session is viable as a pure evidence reducer over one exact V11 package DAG, with append-only verified handoffs, fail-closed dependency gates, explicit non-pass routing, restartable serialization, and no scheduler or host-effect claims.",
  "workUnitsCompleted": [
    "analyze.lifecycle-recovery"
  ],
  "artifacts": [
    {
      "name": "lifecycle-recovery-review.md",
      "mediaType": "text/markdown",
      "content": "# Lifecycle and Recovery Review\n\n## Verdict\n\nA bounded V12 run session is architecture-safe if it is defined as a pure, append-only evidence reducer over one exact verified V11 specialist package. It must not represent dispatch, capacity, execution attempts, cancellation, retries, joins, repository effects, or durable coordination. Core may determine dependency eligibility and accept exact handoff evidence; the external host remains responsible for every effect and for deciding whether an eligible contract is already running.\n\nThe key semantic correction is that V12 `launchable` means dependency-eligible under the fixed package DAG. It cannot mean safe for at-most-once dispatch after a host crash because V12 deliberately has no launch claim or effect-uncertainty state. Documentation and API names must preserve that distinction.\n\n## Source Integrity\n\nBefore use, all nine declared context sources matched both their exact raw SHA-256 digest and byte count: `context.adr-0003`, `context.adr-0004`, `context.correction-design`, `context.executor-boundary`, `context.handbook`, `context.handoff-implementation`, `context.round-4`, `context.v12-goal-synthesis`, and `context.v12-spec`. No source failed its binding.\n\n## Architectural Boundary\n\nThe bounded circuit is:\n\n`verified V11 package + expected digest pair + immutable session + raw handoff bytes | pure create, parse, inspect, and record operations | new immutable session or stable diagnostics`\n\nV12 consumes the selected V11 compilation. It does not re-plan work, alter the roster, assign profiles, construct grants, invoke V10, launch agents, persist values, or update repository and memory state.\n\nOne session selects the complete blueprint roster in the verified compilation. Partial roster selection must reject. A smaller goal must be compiled as a different package rather than weakening a reviewed package at runtime.\n\n## Session Contract\n\nThe session should be a closed JSON value containing only:\n\n- The exact `compilationDigest` and `packageDigest` approved outside the package.\n- A canonical binding for every selected blueprint: agent ID, blueprint digest, direct dependency IDs, work-unit IDs, and generated contract file binding.\n- One owner-reviewed integration gate: either an exact target blueprint ID or an external-all gate requiring every selected blueprint.\n- `revision`, equal to the number of newly accepted distinct handoffs.\n- Canonically ordered accepted-handoff rows.\n- A domain-separated `contentDigest`.\n\nEach accepted-handoff row should contain the agent ID, raw byte count, raw SHA-256 digest, and standard padded base64 for the exact raw UTF-8 handoff bytes. The base64 has no whitespace. This keeps the session self-contained for handoff replay without duplicating the full package. On parse or resume, core decodes and re-runs `verifySpecialistHandoff` against the exact package and expectation. Any mismatch rejects the whole session.\n\nThe state contains no timestamp, random ID, callback, provider, model, prompt, executor, credential, profile, capacity, process, workspace, or storage field. Unknown keys reject. Exact aggregate byte limits must be public constants and checked before constructing a successor.\n\nOne compilation and package digest pair denotes one logical V12 session identity. A second independent run of the same package is not distinguishable by the current V11 handoff because that envelope has no session binding. V12 must not add a decorative run ID and then claim replay isolation. Distinct repeat runs require a new package revision until a future handoff version can bind a session challenge.\n\n## Monotonic Model\n\nLet `B` be the fixed selected blueprint set, `D(b)` the transitive dependency closure of blueprint `b`, and `H` the accepted handoff map keyed by agent ID.\n\nThe stored invariants are:\n\n1. `keys(H)` is a subset of `B`.\n2. There is at most one accepted raw handoff per agent.\n3. Every row has passed the exact V11 package, identity, closure, evidence, media-type, privacy, and control-character checks.\n4. A new row for `b` may be accepted only when every member of `D(b)` already has an accepted `pass` handoff in the prior session.\n5. A successor is `H` plus exactly one new row. Existing rows cannot be deleted, replaced, or reclassified.\n6. Rows are sorted by the repository's exact ordinal text comparator, so accepting independent handoffs in different orders converges to the same normalized state.\n7. An exact replay does not increment `revision` or change `contentDigest`.\n8. A verified non-`pass` outcome is permanent in that session and can never satisfy a dependency or integration gate.\n\nThe only stored transition is accepted evidence. Readiness, blockers, stage, and next action are derived projections rather than mutable flags.\n\n## Public Operations\n\nThe smallest useful operation set is:\n\n1. `createSpecialistRunSession`\n\n   Reconstruct and verify the supplied V11 package against the externally trusted compilation and package digest pair. Bind the complete blueprint roster and integration gate. Return revision zero only after verification succeeds.\n\n2. `parseSpecialistRunSession`\n\n   Parse bounded UTF-8 JSON, validate the closed schema and session digest, reconstruct the same package, compare the roster binding, decode every stored raw handoff, re-run V11 verification, and replay dependency acceptance in canonical topological order. Return no value on any mismatch.\n\n3. `inspectSpecialistRunSession`\n\n   Reverify the package binding and return one immutable inspection containing the complete dependency-eligible set, exact generated contract contents for eligible agents, a closed reason for every other agent, accepted raw evidence bindings, route outcomes, integration readiness, disposition, and next action. Inspection never mutates the session.\n\n4. `recordSpecialistHandoff`\n\n   Verify the session and package first, snapshot the bounded raw bytes, run `verifySpecialistHandoff`, apply deterministic duplicate and dependency checks, enforce the aggregate session limit, and return either a new session, an idempotent replay, or a stable fail-closed rejection. A rejection leaves the exact input session as the complete continuation.\n\nThe record diagnostic precedence must be normative: invalid session or package, invalid raw handoff, unknown or mismatched agent, exact replay, conflicting second handoff, unmet dependencies, aggregate limit, then acceptance. This prevents implementations from exposing different failure classifications for the same input.\n\n## Inspection Semantics\n\nFor each blueprint, inspection derives:\n\n- `accepted_pass` when its accepted handoff outcome is `pass`.\n- `accepted_non_pass` with the exact outcome when a verified non-`pass` handoff exists.\n- `blocked_by_non_pass_dependency` with every transitive blocking agent and outcome.\n- `waiting_for_pass_dependency` with every missing transitive agent.\n- `session_route_required` when its dependencies pass but another accepted non-`pass` outcome has paused new launches.\n- `dependency_eligible` when it is unsettled, every transitive dependency has passed, and no route is required.\n\nThe complete `dependencyEligibleAgentIds` array is canonical and independent of host concurrency width. The exact launchable contract content comes from the reverified package, not from an ID that a callback can substitute.\n\n`integrationReady` is true only when the owner-bound integration gate is satisfied and no accepted non-`pass` outcome exists. For an agent target, every exact transitive dependency must have an accepted `pass` handoff. For an external-all gate, every selected blueprint must have an accepted `pass` handoff. The implementation should share dependency-closure and pass-only logic with `assessSpecialistHandoffs` and add differential tests so the two APIs cannot drift.\n\nThe derived session disposition is a closed union:\n\n- `collecting`: no non-`pass` handoff exists and not every selected blueprint has passed.\n- `route_required`: at least one verified non-`pass` handoff exists.\n- `all_handoffs_pass`: every selected blueprint has an accepted `pass` handoff.\n\n`all_handoffs_pass` is evidence closure for the specialist package. It does not claim merge, repository cleanliness, memory update, provider settlement, or completion of any external host effect.\n\n## Non-Pass Routing\n\nEvery verified non-`pass` handoff is accepted as evidence when its dependencies were satisfied. Its exact workflow outcome, summary, artifacts, evidence, assumptions, risks, and follow-ups remain visible. Core does not coerce it to `failed`, `blocked`, or `pass` and does not invent a retry policy.\n\nOnce any non-`pass` handoff is accepted:\n\n- New launch exposure pauses and inspection returns `route_required`.\n- Dependents remain permanently unsatisfied.\n- All non-pass routes are returned in canonical agent order; no arbitrary winner hides another route.\n- Exact replay remains idempotent.\n- A dependency-ready handoff from independent work already started by the host may still be recorded for source preservation, but acceptance is not proof that it started before the route occurred.\n- Remediation follows the handbook outcome outside core and requires a newly reviewed package or session revision boundary. The failed handoff cannot be overwritten.\n\nThis avoids the Round-4 route-exhaustion contradiction because V12 has neither route budgets nor `any` joins. It reports the exact workflow outcomes rather than deriving a competing terminal code.\n\n## Serialization and Recovery\n\nCanonical session JSON plus the exact verified package is the restart boundary. Parsing must reproduce the same accepted set, disposition, dependency reasons, launchable contract set, integration result, and content digest.\n\nRecovery cases are deterministic:\n\n- Crash before the host persists a returned successor: resume the prior session and replay the same raw handoff.\n- Crash after persistence but before acknowledgment: replay returns the same session with no revision increase.\n- Malformed, stale, substituted, duplicate-conflicting, or dependency-premature handoff: return stable diagnostics and preserve the prior session unchanged.\n- Independent handoffs accepted in different serialized orders: normalization yields the same final session value.\n- Missing package or raw evidence: stop fail-closed; digests alone are not source evidence.\n- Divergent successors produced from one prior session: core does not merge them. The host serializes updates or uses its own compare-and-swap storage.\n- Host crash while an agent may still be live: the session cannot decide whether relaunch is safe. The host must recover or quarantine its execution record. Core continues to report dependency eligibility only.\n\nThere is no hidden process state. Caller persistence is an effect outside core, and V12 makes no durability or distributed atomicity claim.\n\n## Failure Boundaries\n\n| Condition | Core result | Prior session | Host duty |\n| --- | --- | --- | --- |\n| Package reconstruction or expected digest mismatch | Reject | None or unchanged | Recover the exact approved package |\n| Session schema, digest, roster, or raw-evidence mismatch | Reject | Untrusted | Restore a trusted checkpoint |\n| Handoff schema, binding, evidence, media type, or privacy failure | Reject | Unchanged | Preserve raw rejection evidence and route diagnostics |\n| Handoff submitted before all dependencies pass | Reject | Unchanged | Record prerequisite passes first |\n| Exact accepted raw handoff replay | Idempotent replay | Identical | Continue without duplicate work |\n| Different second handoff for one agent | Reject conflict | Unchanged | Create a new reviewed run boundary |\n| Verified non-pass | Accept and route | Monotonically extended | Stop new launches and follow the exact outcome |\n| Aggregate session limit | Reject before transition | Unchanged | Split or compile a bounded package |\n| Host execution uncertainty | Not represented | Unchanged | Resolve externally; never auto-relaunch from session state |\n| Concurrent persistence race | Not prevented | Potential branches | Serialize or use host-owned CAS |\n\n## Round-4 Correction Mapping\n\n| Finding | V12 disposition |\n| --- | --- |\n| P-H1 source loss | Mandatory in bounded form: bind the exact package and preserve exact raw handoffs in the session. The universal chained `RunEvidenceBundle` remains deferred. |\n| P-H2 reviewed roster substitution | Mandatory: verify both package digests and select the complete compiled roster with no callback substitution. |\n| P-M1 authority projection construction | Consumed from V11 compilation; V12 must not rederive or widen it. |\n| A-H1 open semantic projections | Mandatory for V12 session, inspection, transition, and reason shapes. Universal orchestration projections remain deferred. |\n| A-H2 undefined comparator ranks | Mandatory lexical ordering for V12 agent, dependency, blocker, route, and handoff arrays. Unused orchestration ranks remain deferred. |\n| A-H3 incomplete digest registry | Mandatory new domain-separated registry entries for V12 session and derived evidence. Deferred projection formulas are not imported. |\n| A-M1 open WaitGuard | Not present in V12. Capacity and execution wait guards remain deferred. |\n| A-M2 forgeable ExecutionCapture | Not present. Dispatch capture and typed execution rejection remain deferred. |\n| A-M3 callback command bytes | V12 serialized values contain no callbacks and have exact aggregate limits. Universal `runGoal` command sizing remains deferred. |\n| A-M4 undeclared constants | Mandatory exact public V12 limits and kind constants, including reachable aggregate maxima. |\n| A-M5 malformed accumulator rows | Mandatory closed accepted-handoff row keys. The broader accepted-work accumulator remains deferred. |\n| L-H1 provisional any-join loss | Not present. The package DAG uses pass-only dependency closure and one final handoff per agent. Provisional joins remain deferred. |\n| L-H2 width-dependent independence | Mandatory width-independent dependency eligibility. Profile assignment and independence witnesses remain deferred. |\n| L-H3 stranded bound rejection | Mandatory unchanged-session continuation for every pure rejection. Effectful facade continuations remain deferred. |\n| L-M1 conflicting route exhaustion | Mandatory exact non-pass route list with no invented terminal precedence. Route budgets and joins remain deferred. |\n| S-H1 planner-added context authority | Mandatory consumption of the exact verified V11 compilation and its context ceiling; V12 accepts no planner-added source. |\n| S-H2 unbound delivered context | Context delivery and materialization remain host responsibilities. V12 must not claim they occurred. Exact raw handoff bytes are bound and reverified. |\n| S-M1 unscoped attestors | No attestors exist in V12. Claim-scoped attestation remains deferred. |\n| S-M2 unreachable event maxima | No parent orchestration event exists. V12 session and inspection maxima must nevertheless be byte-reachable and boundary-tested. |\n\n## Mandatory V12 Behavior\n\n- Exact package reconstruction and trusted digest-pair verification at creation and resume.\n- Complete immutable roster binding over one fixed acyclic V11 DAG.\n- Closed, canonical, digestible, JSON-serializable session values.\n- Exact raw handoff preservation and V11 verification before state advancement.\n- Append-only at-most-once acceptance with idempotent exact replay.\n- Pass-only transitive dependency and integration readiness.\n- A reason for every non-eligible agent and visible routing for every non-pass outcome.\n- Stable fail-closed diagnostics with no mutation on rejection.\n- Deterministic fresh-process parse and inspection.\n- Explicit host responsibility for persistence, dispatch, effects, and uncertain live work.\n\n## Deferred Runtime Behavior\n\nThe following must remain absent from V12: provider or model selection, runtime profiles, capacity matching, waves, claims, dispatch capabilities, V10 invocation, worktree or sandbox management, permissions enforcement, cancellation, deadlines, retries, provisional joins, route budgets, crash recovery for live effects, distributed CAS, parent event journals, repository witnesses, merge readiness, automatic integration, and durable memory mutation.\n\n## Verification Obligations\n\nImplementation should add negative and boundary coverage for:\n\n1. Wrong compilation digest, wrong package digest, mutated package file, missing package file, and substituted contract.\n2. Initial root eligibility and exact reasons across linear, diamond, fan-out, disconnected, and fan-in DAGs.\n3. Transitive pass-only readiness and agreement with `assessSpecialistHandoffs`.\n4. Every canonical non-pass outcome, permanent dependency blocking, and global route visibility.\n5. Malformed, unknown-agent, stale, wrong-blueprint, wrong-evidence, wrong-media-type, and unsafe-control handoffs.\n6. Handoff-before-dependency rejection with byte-identical prior session.\n7. Exact replay with identical revision and digest.\n8. Conflicting second handoff rejection.\n9. Independent acceptance permutations producing the same normalized final state.\n10. Serialize, parse, reverify, and reinspect equivalence in a fresh process.\n11. Aggregate handoff, base64, session, inspection, and diagnostic byte ceilings at and beyond every limit.\n12. Unknown field rejection and absence of provider, model, executor, prompt, credential, and callback fields.\n13. Packed-consumer use of the complete public operation and constant surface.\n14. Documentation that dependency eligibility is not an at-most-once dispatch guarantee.\n\n## Conclusion\n\nV12 should ship an immutable specialist evidence session, not a reduced universal scheduler. Its monotonic authority comes from the verified package; its progress comes only from exact verified handoffs; its recovery comes from canonical source-preserving serialization and idempotent replay. Everything involving live execution remains an explicit external-host fact or a deferred runtime-control-plane concern."
    }
  ],
  "evidence": [
    {
      "criterionId": "criterion.lifecycle-recovery",
      "requirementId": "evidence.lifecycle-recovery-review",
      "kind": "review",
      "duty": "produce",
      "status": "pass",
      "artifact": "lifecycle-recovery-review.md"
    }
  ],
  "assumptions": [
    "The selected blueprint set is the complete roster from the exact verified V11 compilation; partial package execution is out of scope.",
    "The integration gate is an explicit owner-reviewed session input because core cannot safely infer an integration role from generic DAG topology.",
    "One compilation and package digest pair identifies one logical V12 session until a future handoff schema can bind a distinct session challenge."
  ],
  "risks": [
    "Core tracks dependency eligibility, not dispatch claims, so a restarted host can duplicate still-live work if it treats launchable as an at-most-once execution authorization.",
    "Embedding exact raw handoffs as base64 grows linearly with evidence size and requires reachable aggregate session limits.",
    "After a non-pass route, core can preserve independent returned evidence but cannot prove that the host launched that work before the route occurred."
  ],
  "followUps": [
    "Freeze the exact session, inspection, transition, integration-gate, diagnostic, digest-domain, comparator, and limit declarations in the integrated V12 architecture.",
    "Implement differential dependency-readiness tests against the existing V11 handoff-set assessment.",
    "Keep launch claims, uncertain-effect recovery, retries, cancellation, distributed persistence, and cross-session replay isolation in the deferred runtime layer."
  ]
}