{
  "goalId": "v11.1.readme-release-review",
  "goalRevision": 4,
  "search": {
    "mode": "exact",
    "claim": "exhaustive_partition_search_fixed_scheduler",
    "workUnitCount": 2,
    "evaluatedCandidates": 2,
    "eligibleCandidates": 2,
    "retainedAlternatives": 1,
    "evaluationSetDigest": "sha256:aeae09c58b3e3aa6b5f53e39f3a82cdefd34aac5e0d45de65e98069222d1393b"
  },
  "serialBaseline": {
    "agentCount": 1,
    "projectedMakespan": 10,
    "peakConcurrency": 1,
    "conflictPairs": 0,
    "handoffCount": 0,
    "duplicatedContextBytes": 0,
    "duplicatedPermissionScopes": 0,
    "totalWorkWeight": 9,
    "totalStartupCost": 1,
    "totalHandoffCost": 0
  },
  "selected": {
    "agentCount": 2,
    "projectedMakespan": 6,
    "peakConcurrency": 2,
    "conflictPairs": 0,
    "handoffCount": 0,
    "duplicatedContextBytes": 2897,
    "duplicatedPermissionScopes": 1,
    "totalWorkWeight": 9,
    "totalStartupCost": 2,
    "totalHandoffCost": 0
  },
  "selectionReason": {
    "kind": "lower_metric",
    "decisiveField": "projectedMakespan",
    "selectedValue": 6,
    "serialValue": 10,
    "serialRejectionCodes": []
  },
  "compilationDigest": "sha256:d835edb8382a904d54012caa0641193007b8b46ba79960ba21640ee7a2e0f086",
  "packageDigest": "sha256:044dc3ef45b0988e078145ccf317165113ea3e7a7d7e787be51406d3a5baccc1",
  "agents": [
    {
      "id": "agent.4a46f9924c1597feda7441bbb503b7c8445330fedf0bab277cd9784397d09437",
      "workUnitIds": [
        "review.visual"
      ],
      "contractFile": "agents/agent.4a46f9924c1597feda7441bbb503b7c8445330fedf0bab277cd9784397d09437.md"
    },
    {
      "id": "agent.6a94d5401d38c780124bfeaba9f9b4f2096eb15f921cbad595ce13f030788c5d",
      "workUnitIds": [
        "review.boundary"
      ],
      "contractFile": "agents/agent.6a94d5401d38c780124bfeaba9f9b4f2096eb15f921cbad595ce13f030788c5d.md"
    }
  ],
  "packageVerified": true,
  "runtimeInvoked": false
}
