{
  "compilationDigest": "sha256:e7f6a2d27f613ea1a898b781584039dff8704d88a940965814d45b04a5537920",
  "packageDigest": "sha256:df3ed49a4d38fdbac275b82036dc4354d6b76bac3b2fa97dfbd385c3fdad85b8",
  "manifest": {
    "apiVersion": "swecircuit/specialist/v1alpha1",
    "kind": "SpecialistPackageManifest",
    "goalId": "v12.ide-run-loop.implementation.release-correction",
    "goalRevision": 7,
    "fileDigestAlgorithm": "sha256",
    "fileDigestScope": "raw-file-bytes",
    "compilationDigest": "sha256:e7f6a2d27f613ea1a898b781584039dff8704d88a940965814d45b04a5537920",
    "selectedCandidateId": "team.95637f6ac2bb74c533055e0666c20a7824db48103f5998e8831bdfedc23284e9",
    "launchWaves": [
      {
        "start": 0,
        "agentIds": [
          "agent.5f16c5677b283cd8f5c13655b4b07216731fd3fdb5dfba7c6112471d5bd55c7c"
        ]
      }
    ],
    "compilationFile": "compilation.json",
    "compilationFileDigest": "sha256:6832e04cad3f2d06a63538a3a4d9a57a3db7119337acbfdfceb648e667c9fac8",
    "compilationFileBytes": 61610,
    "agents": [
      {
        "agentId": "agent.5f16c5677b283cd8f5c13655b4b07216731fd3fdb5dfba7c6112471d5bd55c7c",
        "blueprintDigest": "sha256:374f0c75a2a31a2d0fb7aa2462c8e30573b1bd64a91909a9daf0191d95b3e5cd",
        "contractFile": "agents/agent.5f16c5677b283cd8f5c13655b4b07216731fd3fdb5dfba7c6112471d5bd55c7c.md",
        "contractDigest": "sha256:277b71bd417898146b4e60283b0728ee91cec1ece58a72e4a29f5993b40b717d",
        "contractBytes": 21651
      }
    ],
    "integrationFile": "integration.md",
    "integrationDigest": "sha256:7a0507dc24ef0be29b50a63a535da838c9e7a5dff3fa6942faed00708f129200",
    "integrationBytes": 4842,
    "contentDigest": "sha256:8ceab3582d8d2cb0cdfffd640cd0f958739cbf27723c33898eb04ca1c29776f4"
  },
  "files": [
    {
      "path": "agents/agent.5f16c5677b283cd8f5c13655b4b07216731fd3fdb5dfba7c6112471d5bd55c7c.md",
      "mediaType": "text/markdown",
      "bytes": 21651,
      "digest": "sha256:277b71bd417898146b4e60283b0728ee91cec1ece58a72e4a29f5993b40b717d",
      "content": "# Specialist Contract: agent.5f16c5677b283cd8f5c13655b4b07216731fd3fdb5dfba7c6112471d5bd55c7c\n\nCompilation: `sha256:e7f6a2d27f613ea1a898b781584039dff8704d88a940965814d45b04a5537920`\nBlueprint: `sha256:374f0c75a2a31a2d0fb7aa2462c8e30573b1bd64a91909a9daf0191d95b3e5cd`\n\nThis is the exact provider-neutral task contract approved for this specialist. A host may translate it into runtime-specific instructions, but it must not widen authority, add work, omit evidence, or change the handoff.\n\n## Operating Rules\n\n1. Verify every delivered context item against its declared raw SHA-256 digest and byte count before using it.\n2. Work only on the listed work units, Modules, scopes, capabilities, and permissions.\n3. Respect agent dependencies and stop when a stop condition or undeclared decision is reached.\n4. Produce every assigned evidence duty and every required handoff field.\n5. Report assumptions, risks, failed attempts, and follow-up work; do not silently expand scope.\n\nManifest file digests use standard SHA-256 over the exact file bytes. Compilation, blueprint, manifest, and package identities are SWECircuit domain-separated digests and must be verified through the package verifier or another implementation of the published contract.\n\n## Blueprint\n\n```json\n{\n  \"apiVersion\": \"swecircuit/specialist/v1alpha1\",\n  \"kind\": \"AgentBlueprint\",\n  \"id\": \"agent.5f16c5677b283cd8f5c13655b4b07216731fd3fdb5dfba7c6112471d5bd55c7c\",\n  \"goalId\": \"v12.ide-run-loop.implementation.release-correction\",\n  \"goalRevision\": 7,\n  \"goalDigest\": \"sha256:4513970fcccbc4be4173c848fd72bf4b76a4ee52ccc4ae739105d2ffcc30248b\",\n  \"candidateId\": \"team.95637f6ac2bb74c533055e0666c20a7824db48103f5998e8831bdfedc23284e9\",\n  \"workUnitIds\": [\n    \"fix.candidate-evidence-retention.r7\"\n  ],\n  \"objectives\": [\n    {\n      \"workUnitId\": \"fix.candidate-evidence-retention.r7\",\n      \"objective\": \"Preserve exact canonical-gate raw evidence in Git without weakening the repository's general log-ignore policy.\"\n    }\n  ],\n  \"modules\": [\n    {\n      \"id\": \"correction.candidate-evidence-retention\",\n      \"action\": \"Add the narrowest durable ignore-policy exception for canonical-gate stdout and stderr evidence, then make the release-gate wrapper and R2 preparation/revalidation reject any required evidence path that Git still classifies as ignored.\",\n      \"inputPorts\": [\n        {\n          \"name\": \"input\",\n          \"artifactType\": \"IgnoredCanonicalGateEvidence\"\n        }\n      ],\n      \"outputPorts\": [\n        {\n          \"name\": \"output\",\n          \"artifactType\": \"VersionableCandidateBoundGateEvidence\"\n        }\n      ]\n    }\n  ],\n  \"dependencies\": [],\n  \"contextUses\": [\n    {\n      \"sourceId\": \"context.adr-0005\",\n      \"kind\": \"repository\",\n      \"locator\": \"path:docs/specs/v12-ide-run-loop/evidence/implementation/release-correction-r7/inputs/adr-0005.md\",\n      \"digest\": \"sha256:bb585b88635787a7f835e5eb503f6e0053bed624db13b21e9a769d8a5e619b14\",\n      \"bytes\": 9031,\n      \"purposes\": [\n        \"Implement or verify the exact frozen V12 release-correction-r7 contract.\"\n      ],\n      \"workUnitIds\": [\n        \"fix.candidate-evidence-retention.r7\"\n      ],\n      \"readScope\": \"docs/specs/v12-ide-run-loop/evidence/implementation/release-correction-r7/inputs/adr-0005.md\"\n    },\n    {\n      \"sourceId\": \"context.failed-gate-receipt\",\n      \"kind\": \"repository\",\n      \"locator\": \"path:docs/specs/v12-ide-run-loop/evidence/release-review-r2/inputs/canonical-gate-receipt.json\",\n      \"digest\": \"sha256:4c636e486f36c22b74f12fdd4b4470eb9056f63f64eca05058ae6923976bb15c\",\n      \"bytes\": 1221,\n      \"purposes\": [\n        \"Implement or verify the exact frozen V12 release-correction-r7 contract.\"\n      ],\n      \"workUnitIds\": [\n        \"fix.candidate-evidence-retention.r7\"\n      ],\n      \"readScope\": \"docs/specs/v12-ide-run-loop/evidence/release-review-r2/inputs/canonical-gate-receipt.json\"\n    },\n    {\n      \"sourceId\": \"context.failed-gate-stderr\",\n      \"kind\": \"repository\",\n      \"locator\": \"path:docs/specs/v12-ide-run-loop/evidence/release-review-r2/inputs/canonical-gate.stderr.log\",\n      \"digest\": \"sha256:4381d1a9ce1c36beb8723eadfb3619288935b9d095de672c450121c23dc0dfad\",\n      \"bytes\": 11763,\n      \"purposes\": [\n        \"Implement or verify the exact frozen V12 release-correction-r7 contract.\"\n      ],\n      \"workUnitIds\": [\n        \"fix.candidate-evidence-retention.r7\"\n      ],\n      \"readScope\": \"docs/specs/v12-ide-run-loop/evidence/release-review-r2/inputs/canonical-gate.stderr.log\"\n    },\n    {\n      \"sourceId\": \"context.failed-gate-stdout\",\n      \"kind\": \"repository\",\n      \"locator\": \"path:docs/specs/v12-ide-run-loop/evidence/release-review-r2/inputs/canonical-gate.stdout.log\",\n      \"digest\": \"sha256:afb6b266dd504cbf89d2cb55b6f9c5c6872fd5636acef8848e2105257aecef12\",\n      \"bytes\": 295768,\n      \"purposes\": [\n        \"Implement or verify the exact frozen V12 release-correction-r7 contract.\"\n      ],\n      \"workUnitIds\": [\n        \"fix.candidate-evidence-retention.r7\"\n      ],\n      \"readScope\": \"docs/specs/v12-ide-run-loop/evidence/release-review-r2/inputs/canonical-gate.stdout.log\"\n    },\n    {\n      \"sourceId\": \"context.gitignore\",\n      \"kind\": \"repository\",\n      \"locator\": \"path:.gitignore\",\n      \"digest\": \"sha256:ad4ce9d55303f62f262e18b7e47710d9e43049625c704cbaa46cbb4487bbc8d8\",\n      \"bytes\": 340,\n      \"purposes\": [\n        \"Implement or verify the exact frozen V12 release-correction-r7 contract.\"\n      ],\n      \"workUnitIds\": [\n        \"fix.candidate-evidence-retention.r7\"\n      ],\n      \"readScope\": \".gitignore\"\n    },\n    {\n      \"sourceId\": \"context.package\",\n      \"kind\": \"repository\",\n      \"locator\": \"path:package.json\",\n      \"digest\": \"sha256:43414ace7e294a9a173ee78ab33baa5791959921f5da2a1c7b3b69d081938df2\",\n      \"bytes\": 2946,\n      \"purposes\": [\n        \"Implement or verify the exact frozen V12 release-correction-r7 contract.\"\n      ],\n      \"workUnitIds\": [\n        \"fix.candidate-evidence-retention.r7\"\n      ],\n      \"readScope\": \"package.json\"\n    },\n    {\n      \"sourceId\": \"context.release-correction-r6-approval\",\n      \"kind\": \"repository\",\n      \"locator\": \"path:docs/specs/v12-ide-run-loop/evidence/implementation/release-correction-r6/approval.json\",\n      \"digest\": \"sha256:b0a48bde829f601ec4d11abeb5c0f54dcb7123182d2c1fbdb405fc251b28a27c\",\n      \"bytes\": 641,\n      \"purposes\": [\n        \"Implement or verify the exact frozen V12 release-correction-r7 contract.\"\n      ],\n      \"workUnitIds\": [\n        \"fix.candidate-evidence-retention.r7\"\n      ],\n      \"readScope\": \"docs/specs/v12-ide-run-loop/evidence/implementation/release-correction-r6/approval.json\"\n    },\n    {\n      \"sourceId\": \"context.release-correction-r6-consumer-handoff\",\n      \"kind\": \"repository\",\n      \"locator\": \"path:docs/specs/v12-ide-run-loop/evidence/implementation/release-correction-r6/handoffs/agent.9579818ca2843121c26d1c38b48b0f78421bcba0ed39783ced3bfd842a45904e.json\",\n      \"digest\": \"sha256:939099add2852e3dfe14b307fc55e46c89b56a1dd0c735d15bf35e82f99a5a68\",\n      \"bytes\": 5291,\n      \"purposes\": [\n        \"Implement or verify the exact frozen V12 release-correction-r7 contract.\"\n      ],\n      \"workUnitIds\": [\n        \"fix.candidate-evidence-retention.r7\"\n      ],\n      \"readScope\": \"docs/specs/v12-ide-run-loop/evidence/implementation/release-correction-r6/handoffs/agent.9579818ca2843121c26d1c38b48b0f78421bcba0ed39783ced3bfd842a45904e.json\"\n    },\n    {\n      \"sourceId\": \"context.release-correction-r6-gate-handoff\",\n      \"kind\": \"repository\",\n      \"locator\": \"path:docs/specs/v12-ide-run-loop/evidence/implementation/release-correction-r6/handoffs/agent.4a4cca8bce6a03e1f36dfd28b9505ff33920a045636f8715b10110fdbd408985.json\",\n      \"digest\": \"sha256:3c95ca87255613bdcb96f0a894a03ce012c4d5662a3379230c07166e56fcf33b\",\n      \"bytes\": 5061,\n      \"purposes\": [\n        \"Implement or verify the exact frozen V12 release-correction-r7 contract.\"\n      ],\n      \"workUnitIds\": [\n        \"fix.candidate-evidence-retention.r7\"\n      ],\n      \"readScope\": \"docs/specs/v12-ide-run-loop/evidence/implementation/release-correction-r6/handoffs/agent.4a4cca8bce6a03e1f36dfd28b9505ff33920a045636f8715b10110fdbd408985.json\"\n    },\n    {\n      \"sourceId\": \"context.release-correction-r6-package\",\n      \"kind\": \"repository\",\n      \"locator\": \"path:docs/specs/v12-ide-run-loop/evidence/implementation/release-correction-r6/package-envelope.json\",\n      \"digest\": \"sha256:08fba946e7d8fd47b112322a4f8ea954922d230de6d2b9fac234bdd297f6540f\",\n      \"bytes\": 152251,\n      \"purposes\": [\n        \"Implement or verify the exact frozen V12 release-correction-r7 contract.\"\n      ],\n      \"workUnitIds\": [\n        \"fix.candidate-evidence-retention.r7\"\n      ],\n      \"readScope\": \"docs/specs/v12-ide-run-loop/evidence/implementation/release-correction-r6/package-envelope.json\"\n    },\n    {\n      \"sourceId\": \"context.release-correction-r6-report\",\n      \"kind\": \"repository\",\n      \"locator\": \"path:docs/specs/v12-ide-run-loop/evidence/implementation/release-correction-r6/handoff-verification.json\",\n      \"digest\": \"sha256:3d3a406acd342a7c32d22e7cd3a92a0c7db89d74af50d9d394da9a93830c76fb\",\n      \"bytes\": 1998,\n      \"purposes\": [\n        \"Implement or verify the exact frozen V12 release-correction-r7 contract.\"\n      ],\n      \"workUnitIds\": [\n        \"fix.candidate-evidence-retention.r7\"\n      ],\n      \"readScope\": \"docs/specs/v12-ide-run-loop/evidence/implementation/release-correction-r6/handoff-verification.json\"\n    },\n    {\n      \"sourceId\": \"context.release-gate\",\n      \"kind\": \"repository\",\n      \"locator\": \"path:scripts/run-v12-release-gate.mjs\",\n      \"digest\": \"sha256:552d8a11ed3f05156b935e9f461083ac9e1f00897bc797a0d3fe7c7a7d25822b\",\n      \"bytes\": 6999,\n      \"purposes\": [\n        \"Implement or verify the exact frozen V12 release-correction-r7 contract.\"\n      ],\n      \"workUnitIds\": [\n        \"fix.candidate-evidence-retention.r7\"\n      ],\n      \"readScope\": \"scripts/run-v12-release-gate.mjs\"\n    },\n    {\n      \"sourceId\": \"context.release-review-r2-harness\",\n      \"kind\": \"repository\",\n      \"locator\": \"path:docs/specs/v12-ide-run-loop/evidence/release-review-r2/run-release-review.mjs\",\n      \"digest\": \"sha256:b41e59d7cf5d905a088c7445f7ede71019be8a15aa17273fe216a60af8fc149c\",\n      \"bytes\": 66496,\n      \"purposes\": [\n        \"Implement or verify the exact frozen V12 release-correction-r7 contract.\"\n      ],\n      \"workUnitIds\": [\n        \"fix.candidate-evidence-retention.r7\"\n      ],\n      \"readScope\": \"docs/specs/v12-ide-run-loop/evidence/release-review-r2/run-release-review.mjs\"\n    },\n    {\n      \"sourceId\": \"context.release-review-r2-verifier\",\n      \"kind\": \"repository\",\n      \"locator\": \"path:docs/specs/v12-ide-run-loop/evidence/release-review-r2/verify-release-review-handoffs.mjs\",\n      \"digest\": \"sha256:e30bbf7548d6481935d14db57630e4e5bdaa9aff2df56337b957d07acc83d2aa\",\n      \"bytes\": 6984,\n      \"purposes\": [\n        \"Implement or verify the exact frozen V12 release-correction-r7 contract.\"\n      ],\n      \"workUnitIds\": [\n        \"fix.candidate-evidence-retention.r7\"\n      ],\n      \"readScope\": \"docs/specs/v12-ide-run-loop/evidence/release-review-r2/verify-release-review-handoffs.mjs\"\n    },\n    {\n      \"sourceId\": \"context.run-contract\",\n      \"kind\": \"repository\",\n      \"locator\": \"path:docs/specs/v12-ide-run-loop/evidence/implementation/release-correction-r7/inputs/specialist-run-contract.md\",\n      \"digest\": \"sha256:9b3340f0c95fc33abe945b35e3d1e0520392dee5ea01c3f78f24cb65473fa242\",\n      \"bytes\": 17133,\n      \"purposes\": [\n        \"Implement or verify the exact frozen V12 release-correction-r7 contract.\"\n      ],\n      \"workUnitIds\": [\n        \"fix.candidate-evidence-retention.r7\"\n      ],\n      \"readScope\": \"docs/specs/v12-ide-run-loop/evidence/implementation/release-correction-r7/inputs/specialist-run-contract.md\"\n    },\n    {\n      \"sourceId\": \"context.test-plan\",\n      \"kind\": \"repository\",\n      \"locator\": \"path:docs/specs/v12-ide-run-loop/evidence/implementation/release-correction-r7/inputs/test-plan.md\",\n      \"digest\": \"sha256:ffa2102cbcf6d145d4f5b0ddbc26b9b02f86433a22b4b99b9f5cb084f605d7ec\",\n      \"bytes\": 2506,\n      \"purposes\": [\n        \"Implement or verify the exact frozen V12 release-correction-r7 contract.\"\n      ],\n      \"workUnitIds\": [\n        \"fix.candidate-evidence-retention.r7\"\n      ],\n      \"readScope\": \"docs/specs/v12-ide-run-loop/evidence/implementation/release-correction-r7/inputs/test-plan.md\"\n    },\n    {\n      \"sourceId\": \"context.v12-spec\",\n      \"kind\": \"repository\",\n      \"locator\": \"path:docs/specs/v12-ide-run-loop/evidence/implementation/release-correction-r7/inputs/spec.md\",\n      \"digest\": \"sha256:b0a3610c935cacf032e9c142d9436b6f620227667c64c5bf0e296eaf4f571ab1\",\n      \"bytes\": 5478,\n      \"purposes\": [\n        \"Implement or verify the exact frozen V12 release-correction-r7 contract.\"\n      ],\n      \"workUnitIds\": [\n        \"fix.candidate-evidence-retention.r7\"\n      ],\n      \"readScope\": \"docs/specs/v12-ide-run-loop/evidence/implementation/release-correction-r7/inputs/spec.md\"\n    }\n  ],\n  \"authority\": {\n    \"requiredCapabilities\": [\n      \"fix.candidate-evidence-retention\"\n    ],\n    \"scope\": {\n      \"read\": [\n        \".gitignore\",\n        \"docs/specs/v12-ide-run-loop/evidence/implementation/release-correction-r6/approval.json\",\n        \"docs/specs/v12-ide-run-loop/evidence/implementation/release-correction-r6/handoff-verification.json\",\n        \"docs/specs/v12-ide-run-loop/evidence/implementation/release-correction-r6/handoffs/agent.4a4cca8bce6a03e1f36dfd28b9505ff33920a045636f8715b10110fdbd408985.json\",\n        \"docs/specs/v12-ide-run-loop/evidence/implementation/release-correction-r6/handoffs/agent.9579818ca2843121c26d1c38b48b0f78421bcba0ed39783ced3bfd842a45904e.json\",\n        \"docs/specs/v12-ide-run-loop/evidence/implementation/release-correction-r6/package-envelope.json\",\n        \"docs/specs/v12-ide-run-loop/evidence/implementation/release-correction-r7/inputs/adr-0005.md\",\n        \"docs/specs/v12-ide-run-loop/evidence/implementation/release-correction-r7/inputs/spec.md\",\n        \"docs/specs/v12-ide-run-loop/evidence/implementation/release-correction-r7/inputs/specialist-run-contract.md\",\n        \"docs/specs/v12-ide-run-loop/evidence/implementation/release-correction-r7/inputs/test-plan.md\",\n        \"docs/specs/v12-ide-run-loop/evidence/release-review-r2/inputs/canonical-gate-receipt.json\",\n        \"docs/specs/v12-ide-run-loop/evidence/release-review-r2/inputs/canonical-gate.stderr.log\",\n        \"docs/specs/v12-ide-run-loop/evidence/release-review-r2/inputs/canonical-gate.stdout.log\",\n        \"docs/specs/v12-ide-run-loop/evidence/release-review-r2/run-release-review.mjs\",\n        \"docs/specs/v12-ide-run-loop/evidence/release-review-r2/verify-release-review-handoffs.mjs\",\n        \"package.json\",\n        \"scripts/run-v12-release-gate.mjs\"\n      ],\n      \"write\": [\n        \".gitignore\",\n        \"docs/specs/v12-ide-run-loop/evidence/release-review-r2/run-release-review.mjs\",\n        \"scripts/run-v12-release-gate.mjs\"\n      ],\n      \"conflictZones\": [\n        \".gitignore\",\n        \"docs/specs/v12-ide-run-loop/evidence/release-review-r2/run-release-review.mjs\",\n        \"scripts/run-v12-release-gate.mjs\"\n      ]\n    },\n    \"permissions\": [\n      {\n        \"kind\": \"filesystem.read\",\n        \"scopes\": [\n          \".gitignore\",\n          \"docs/specs/v12-ide-run-loop/evidence/implementation/release-correction-r6/approval.json\",\n          \"docs/specs/v12-ide-run-loop/evidence/implementation/release-correction-r6/handoff-verification.json\",\n          \"docs/specs/v12-ide-run-loop/evidence/implementation/release-correction-r6/handoffs/agent.4a4cca8bce6a03e1f36dfd28b9505ff33920a045636f8715b10110fdbd408985.json\",\n          \"docs/specs/v12-ide-run-loop/evidence/implementation/release-correction-r6/handoffs/agent.9579818ca2843121c26d1c38b48b0f78421bcba0ed39783ced3bfd842a45904e.json\",\n          \"docs/specs/v12-ide-run-loop/evidence/implementation/release-correction-r6/package-envelope.json\",\n          \"docs/specs/v12-ide-run-loop/evidence/implementation/release-correction-r7/inputs/adr-0005.md\",\n          \"docs/specs/v12-ide-run-loop/evidence/implementation/release-correction-r7/inputs/spec.md\",\n          \"docs/specs/v12-ide-run-loop/evidence/implementation/release-correction-r7/inputs/specialist-run-contract.md\",\n          \"docs/specs/v12-ide-run-loop/evidence/implementation/release-correction-r7/inputs/test-plan.md\",\n          \"docs/specs/v12-ide-run-loop/evidence/release-review-r2/inputs/canonical-gate-receipt.json\",\n          \"docs/specs/v12-ide-run-loop/evidence/release-review-r2/inputs/canonical-gate.stderr.log\",\n          \"docs/specs/v12-ide-run-loop/evidence/release-review-r2/inputs/canonical-gate.stdout.log\",\n          \"docs/specs/v12-ide-run-loop/evidence/release-review-r2/run-release-review.mjs\",\n          \"docs/specs/v12-ide-run-loop/evidence/release-review-r2/verify-release-review-handoffs.mjs\",\n          \"package.json\",\n          \"scripts/run-v12-release-gate.mjs\"\n        ]\n      },\n      {\n        \"kind\": \"filesystem.write\",\n        \"scopes\": [\n          \".gitignore\",\n          \"docs/specs/v12-ide-run-loop/evidence/release-review-r2/run-release-review.mjs\",\n          \"scripts/run-v12-release-gate.mjs\"\n        ]\n      },\n      {\n        \"kind\": \"process.spawn\",\n        \"scopes\": [\n          \"git\",\n          \"node\",\n          \"npm\",\n          \"powershell\"\n        ]\n      }\n    ],\n    \"forbiddenEffects\": [\n      \"Do not use network access, change Git state, launch descendants, write outside the exact scope, or claim that core performs host effects.\"\n    ]\n  },\n  \"evidenceDuties\": [\n    {\n      \"criterionId\": \"criterion.fix.candidate-evidence-retention.r7\",\n      \"criterion\": \"Preserve exact canonical-gate raw evidence in Git without weakening the repository's general log-ignore policy.\",\n      \"requirementId\": \"evidence.candidate-evidence-retention.r7\",\n      \"kind\": \"review\",\n      \"duty\": \"produce\",\n      \"description\": \"Authenticate unchanged candidate-1 bytes, prove legacy and synthetic candidate-addressed canonical logs are not ignored while unrelated logs remain ignored, prove wrapper/R2 path parity and fail-closed behavior, and provide syntax, format, and focused regression results.\",\n      \"independentFromProducer\": false\n    }\n  ],\n  \"handoff\": {\n    \"destination\": \"codex.main\",\n    \"artifacts\": [\n      \"candidate-evidence-retention-correction-r7.md\"\n    ],\n    \"requiredFields\": [\n      \"apiVersion\",\n      \"kind\",\n      \"outcome\",\n      \"destination\",\n      \"goal\",\n      \"agent\",\n      \"compilationDigest\",\n      \"summary\",\n      \"workUnitsCompleted\",\n      \"artifacts\",\n      \"evidence\",\n      \"assumptions\",\n      \"risks\",\n      \"followUps\"\n    ]\n  },\n  \"stopConditions\": [\n    \"If native apply_patch fails before mutation because of the host sandbox, an exact precondition-hash-guarded PowerShell write is allowed within the declared write scope; verify the resulting file bytes immediately.\",\n    \"Return only the concrete closed SpecialistAgentHandoff JSON shape from the generated contract.\",\n    \"Run only local focused verification allowed by the contract and report every failing command truthfully.\",\n    \"Stop if any declared source is unavailable or fails its exact digest and byte binding.\",\n    \"Write only the exact declared write scope; do not change Git state, use the network, launch descendants, or widen the public contract.\"\n  ],\n  \"contentDigest\": \"sha256:374f0c75a2a31a2d0fb7aa2462c8e30573b1bd64a91909a9daf0191d95b3e5cd\"\n}\n```\n\n## Required Handoff Envelope\n\nReturn one strict UTF-8 JSON object with exactly the shape below. Replace the summary and artifact content, but do not add keys or substitute the blueprint evidence-duty shape.\n\n- Artifact content is always a string, including for application/json.\n- Evidence entries contain exactly criterionId, requirementId, kind, duty, status, and artifact.\n- A pass must list every owned work unit, exact artifact name, and exact evidence duty. A non-pass outcome lists only work actually completed and preserves bounded failure evidence.\n- If a stop condition explicitly requires a stricter custom envelope, the host must provide that closed schema; it must retain the standard goal, agent, compilation, artifact, evidence, and outcome bindings shown here.\n\n```json\n{\n  \"apiVersion\": \"swecircuit/specialist/v1alpha1\",\n  \"kind\": \"SpecialistAgentHandoff\",\n  \"outcome\": \"pass\",\n  \"destination\": \"codex.main\",\n  \"goal\": {\n    \"id\": \"v12.ide-run-loop.implementation.release-correction\",\n    \"revision\": 7,\n    \"digest\": \"sha256:4513970fcccbc4be4173c848fd72bf4b76a4ee52ccc4ae739105d2ffcc30248b\"\n  },\n  \"agent\": {\n    \"id\": \"agent.5f16c5677b283cd8f5c13655b4b07216731fd3fdb5dfba7c6112471d5bd55c7c\",\n    \"blueprintDigest\": \"sha256:374f0c75a2a31a2d0fb7aa2462c8e30573b1bd64a91909a9daf0191d95b3e5cd\"\n  },\n  \"compilationDigest\": \"sha256:e7f6a2d27f613ea1a898b781584039dff8704d88a940965814d45b04a5537920\",\n  \"summary\": \"Replace with a concise result summary.\",\n  \"workUnitsCompleted\": [\n    \"fix.candidate-evidence-retention.r7\"\n  ],\n  \"artifacts\": [\n    {\n      \"name\": \"candidate-evidence-retention-correction-r7.md\",\n      \"mediaType\": \"text/markdown\",\n      \"content\": \"Replace with the complete artifact content.\"\n    }\n  ],\n  \"evidence\": [\n    {\n      \"criterionId\": \"criterion.fix.candidate-evidence-retention.r7\",\n      \"requirementId\": \"evidence.candidate-evidence-retention.r7\",\n      \"kind\": \"review\",\n      \"duty\": \"produce\",\n      \"status\": \"pass\",\n      \"artifact\": \"candidate-evidence-retention-correction-r7.md\"\n    }\n  ],\n  \"assumptions\": [],\n  \"risks\": [],\n  \"followUps\": []\n}\n```\n"
    },
    {
      "path": "compilation.json",
      "mediaType": "application/json",
      "bytes": 61610,
      "digest": "sha256:6832e04cad3f2d06a63538a3a4d9a57a3db7119337acbfdfceb648e667c9fac8",
      "content": "{\n  \"apiVersion\": \"swecircuit/specialist/v1alpha1\",\n  \"kind\": \"AgentBlueprintCompilation\",\n  \"goal\": {\n    \"apiVersion\": \"swecircuit/specialist/v1alpha1\",\n    \"kind\": \"GoalContract\",\n    \"id\": \"v12.ide-run-loop.implementation.release-correction\",\n    \"revision\": 7,\n    \"objective\": \"Make exact canonical-gate raw logs versionable and make both the gate wrapper and R2 review fail closed when required evidence paths are ignored.\",\n    \"integrationOwner\": \"codex.main\",\n    \"assumptions\": [\n      {\n        \"id\": \"assumption.architecture-frozen\",\n        \"statement\": \"ADR 0005 and the Specialist Run contract are the complete implementation authority.\",\n        \"rationale\": \"Architecture fan-in passed and no blocking decision remains.\"\n      },\n      {\n        \"id\": \"assumption.candidate-one-bytes-remain-immutable\",\n        \"statement\": \"Revision 7 may make the candidate-1 raw logs visible to Git but must not change their bytes, paths, receipt bindings, or failed outcome.\",\n        \"rationale\": \"The failed attempt remains primary source evidence and cannot be rewritten to simplify retention.\"\n      },\n      {\n        \"id\": \"assumption.host-edit-fallback\",\n        \"statement\": \"After native apply_patch fails before mutation, the host may perform an exact precondition-hash-guarded PowerShell write inside the approved scope.\",\n        \"rationale\": \"Foundation Revision 1 proved the temporary worktree patch helper is unavailable while bounded escalated PowerShell writes remain auditable and fail closed.\"\n      },\n      {\n        \"id\": \"assumption.host-effects-external\",\n        \"statement\": \"All runtime, persistence, Git, merge, and memory effects remain external to core.\",\n        \"rationale\": \"V12 is a pure evidence session, not the deferred universal scheduler.\"\n      },\n      {\n        \"id\": \"assumption.raw-gate-logs-must-be-versionable\",\n        \"statement\": \"The canonical receipt is not durable release evidence unless its exact stdout and stderr source bytes can be committed and recovered from a fresh clone.\",\n        \"rationale\": \"The repository currently ignores every .log file, including both exact candidate-1 gate logs and future candidate-addressed gate logs.\"\n      }\n    ],\n    \"unresolvedDecisions\": [],\n    \"acceptanceCriteria\": [\n      {\n        \"id\": \"criterion.fix.candidate-evidence-retention.r7\",\n        \"description\": \"Preserve exact canonical-gate raw evidence in Git without weakening the repository's general log-ignore policy.\",\n        \"evidenceRequirements\": [\n          {\n            \"id\": \"evidence.candidate-evidence-retention.r7\",\n            \"kind\": \"review\",\n            \"duty\": \"produce\",\n            \"description\": \"Authenticate unchanged candidate-1 bytes, prove legacy and synthetic candidate-addressed canonical logs are not ignored while unrelated logs remain ignored, prove wrapper/R2 path parity and fail-closed behavior, and provide syntax, format, and focused regression results.\",\n            \"independentFromProducer\": false\n          }\n        ]\n      }\n    ],\n    \"contextSources\": [\n      {\n        \"id\": \"context.adr-0005\",\n        \"kind\": \"repository\",\n        \"locator\": \"path:docs/specs/v12-ide-run-loop/evidence/implementation/release-correction-r7/inputs/adr-0005.md\",\n        \"digest\": \"sha256:bb585b88635787a7f835e5eb503f6e0053bed624db13b21e9a769d8a5e619b14\",\n        \"bytes\": 9031,\n        \"description\": \"Accepted immutable Specialist Run Session decision.\",\n        \"allowedWorkUnits\": [\n          \"fix.candidate-evidence-retention.r7\"\n        ],\n        \"readScope\": \"docs/specs/v12-ide-run-loop/evidence/implementation/release-correction-r7/inputs/adr-0005.md\"\n      },\n      {\n        \"id\": \"context.failed-gate-receipt\",\n        \"kind\": \"repository\",\n        \"locator\": \"path:docs/specs/v12-ide-run-loop/evidence/release-review-r2/inputs/canonical-gate-receipt.json\",\n        \"digest\": \"sha256:4c636e486f36c22b74f12fdd4b4470eb9056f63f64eca05058ae6923976bb15c\",\n        \"bytes\": 1221,\n        \"description\": \"Immutable candidate-1 canonical-gate failure receipt.\",\n        \"allowedWorkUnits\": [\n          \"fix.candidate-evidence-retention.r7\"\n        ],\n        \"readScope\": \"docs/specs/v12-ide-run-loop/evidence/release-review-r2/inputs/canonical-gate-receipt.json\"\n      },\n      {\n        \"id\": \"context.failed-gate-stderr\",\n        \"kind\": \"repository\",\n        \"locator\": \"path:docs/specs/v12-ide-run-loop/evidence/release-review-r2/inputs/canonical-gate.stderr.log\",\n        \"digest\": \"sha256:4381d1a9ce1c36beb8723eadfb3619288935b9d095de672c450121c23dc0dfad\",\n        \"bytes\": 11763,\n        \"description\": \"Exact raw candidate-1 canonical-gate stderr bytes.\",\n        \"allowedWorkUnits\": [\n          \"fix.candidate-evidence-retention.r7\"\n        ],\n        \"readScope\": \"docs/specs/v12-ide-run-loop/evidence/release-review-r2/inputs/canonical-gate.stderr.log\"\n      },\n      {\n        \"id\": \"context.failed-gate-stdout\",\n        \"kind\": \"repository\",\n        \"locator\": \"path:docs/specs/v12-ide-run-loop/evidence/release-review-r2/inputs/canonical-gate.stdout.log\",\n        \"digest\": \"sha256:afb6b266dd504cbf89d2cb55b6f9c5c6872fd5636acef8848e2105257aecef12\",\n        \"bytes\": 295768,\n        \"description\": \"Exact raw candidate-1 canonical-gate stdout bytes.\",\n        \"allowedWorkUnits\": [\n          \"fix.candidate-evidence-retention.r7\"\n        ],\n        \"readScope\": \"docs/specs/v12-ide-run-loop/evidence/release-review-r2/inputs/canonical-gate.stdout.log\"\n      },\n      {\n        \"id\": \"context.gitignore\",\n        \"kind\": \"repository\",\n        \"locator\": \"path:.gitignore\",\n        \"digest\": \"sha256:ad4ce9d55303f62f262e18b7e47710d9e43049625c704cbaa46cbb4487bbc8d8\",\n        \"bytes\": 340,\n        \"description\": \"Repository ignore policy that currently suppresses canonical-gate raw log evidence.\",\n        \"allowedWorkUnits\": [\n          \"fix.candidate-evidence-retention.r7\"\n        ],\n        \"readScope\": \".gitignore\"\n      },\n      {\n        \"id\": \"context.package\",\n        \"kind\": \"repository\",\n        \"locator\": \"path:package.json\",\n        \"digest\": \"sha256:43414ace7e294a9a173ee78ab33baa5791959921f5da2a1c7b3b69d081938df2\",\n        \"bytes\": 2946,\n        \"description\": \"Existing package scripts and export map.\",\n        \"allowedWorkUnits\": [\n          \"fix.candidate-evidence-retention.r7\"\n        ],\n        \"readScope\": \"package.json\"\n      },\n      {\n        \"id\": \"context.release-correction-r6-approval\",\n        \"kind\": \"repository\",\n        \"locator\": \"path:docs/specs/v12-ide-run-loop/evidence/implementation/release-correction-r6/approval.json\",\n        \"digest\": \"sha256:b0a48bde829f601ec4d11abeb5c0f54dcb7123182d2c1fbdb405fc251b28a27c\",\n        \"bytes\": 641,\n        \"description\": \"Exact owner approval for the revision-6 package.\",\n        \"allowedWorkUnits\": [\n          \"fix.candidate-evidence-retention.r7\"\n        ],\n        \"readScope\": \"docs/specs/v12-ide-run-loop/evidence/implementation/release-correction-r6/approval.json\"\n      },\n      {\n        \"id\": \"context.release-correction-r6-consumer-handoff\",\n        \"kind\": \"repository\",\n        \"locator\": \"path:docs/specs/v12-ide-run-loop/evidence/implementation/release-correction-r6/handoffs/agent.9579818ca2843121c26d1c38b48b0f78421bcba0ed39783ced3bfd842a45904e.json\",\n        \"digest\": \"sha256:939099add2852e3dfe14b307fc55e46c89b56a1dd0c735d15bf35e82f99a5a68\",\n        \"bytes\": 5291,\n        \"description\": \"Exact revision-6 consumer and architecture parity PASS handoff.\",\n        \"allowedWorkUnits\": [\n          \"fix.candidate-evidence-retention.r7\"\n        ],\n        \"readScope\": \"docs/specs/v12-ide-run-loop/evidence/implementation/release-correction-r6/handoffs/agent.9579818ca2843121c26d1c38b48b0f78421bcba0ed39783ced3bfd842a45904e.json\"\n      },\n      {\n        \"id\": \"context.release-correction-r6-gate-handoff\",\n        \"kind\": \"repository\",\n        \"locator\": \"path:docs/specs/v12-ide-run-loop/evidence/implementation/release-correction-r6/handoffs/agent.4a4cca8bce6a03e1f36dfd28b9505ff33920a045636f8715b10110fdbd408985.json\",\n        \"digest\": \"sha256:3c95ca87255613bdcb96f0a894a03ce012c4d5662a3379230c07166e56fcf33b\",\n        \"bytes\": 5061,\n        \"description\": \"Exact revision-6 candidate-gate identity PASS handoff.\",\n        \"allowedWorkUnits\": [\n          \"fix.candidate-evidence-retention.r7\"\n        ],\n        \"readScope\": \"docs/specs/v12-ide-run-loop/evidence/implementation/release-correction-r6/handoffs/agent.4a4cca8bce6a03e1f36dfd28b9505ff33920a045636f8715b10110fdbd408985.json\"\n      },\n      {\n        \"id\": \"context.release-correction-r6-package\",\n        \"kind\": \"repository\",\n        \"locator\": \"path:docs/specs/v12-ide-run-loop/evidence/implementation/release-correction-r6/package-envelope.json\",\n        \"digest\": \"sha256:08fba946e7d8fd47b112322a4f8ea954922d230de6d2b9fac234bdd297f6540f\",\n        \"bytes\": 152251,\n        \"description\": \"Owner-approved revision-6 consumer-parity and candidate-identity package.\",\n        \"allowedWorkUnits\": [\n          \"fix.candidate-evidence-retention.r7\"\n        ],\n        \"readScope\": \"docs/specs/v12-ide-run-loop/evidence/implementation/release-correction-r6/package-envelope.json\"\n      },\n      {\n        \"id\": \"context.release-correction-r6-report\",\n        \"kind\": \"repository\",\n        \"locator\": \"path:docs/specs/v12-ide-run-loop/evidence/implementation/release-correction-r6/handoff-verification.json\",\n        \"digest\": \"sha256:3d3a406acd342a7c32d22e7cd3a92a0c7db89d74af50d9d394da9a93830c76fb\",\n        \"bytes\": 1998,\n        \"description\": \"Complete revision-6 PASS handoff report.\",\n        \"allowedWorkUnits\": [\n          \"fix.candidate-evidence-retention.r7\"\n        ],\n        \"readScope\": \"docs/specs/v12-ide-run-loop/evidence/implementation/release-correction-r6/handoff-verification.json\"\n      },\n      {\n        \"id\": \"context.release-gate\",\n        \"kind\": \"repository\",\n        \"locator\": \"path:scripts/run-v12-release-gate.mjs\",\n        \"digest\": \"sha256:552d8a11ed3f05156b935e9f461083ac9e1f00897bc797a0d3fe7c7a7d25822b\",\n        \"bytes\": 6999,\n        \"description\": \"Current candidate-bound canonical gate wrapper.\",\n        \"allowedWorkUnits\": [\n          \"fix.candidate-evidence-retention.r7\"\n        ],\n        \"readScope\": \"scripts/run-v12-release-gate.mjs\"\n      },\n      {\n        \"id\": \"context.release-review-r2-harness\",\n        \"kind\": \"repository\",\n        \"locator\": \"path:docs/specs/v12-ide-run-loop/evidence/release-review-r2/run-release-review.mjs\",\n        \"digest\": \"sha256:b41e59d7cf5d905a088c7445f7ede71019be8a15aa17273fe216a60af8fc149c\",\n        \"bytes\": 66496,\n        \"description\": \"Current candidate-bound R2 release-review preparation and compilation harness.\",\n        \"allowedWorkUnits\": [\n          \"fix.candidate-evidence-retention.r7\"\n        ],\n        \"readScope\": \"docs/specs/v12-ide-run-loop/evidence/release-review-r2/run-release-review.mjs\"\n      },\n      {\n        \"id\": \"context.release-review-r2-verifier\",\n        \"kind\": \"repository\",\n        \"locator\": \"path:docs/specs/v12-ide-run-loop/evidence/release-review-r2/verify-release-review-handoffs.mjs\",\n        \"digest\": \"sha256:e30bbf7548d6481935d14db57630e4e5bdaa9aff2df56337b957d07acc83d2aa\",\n        \"bytes\": 6984,\n        \"description\": \"Current exact R2 reviewer handoff verifier.\",\n        \"allowedWorkUnits\": [\n          \"fix.candidate-evidence-retention.r7\"\n        ],\n        \"readScope\": \"docs/specs/v12-ide-run-loop/evidence/release-review-r2/verify-release-review-handoffs.mjs\"\n      },\n      {\n        \"id\": \"context.run-contract\",\n        \"kind\": \"repository\",\n        \"locator\": \"path:docs/specs/v12-ide-run-loop/evidence/implementation/release-correction-r7/inputs/specialist-run-contract.md\",\n        \"digest\": \"sha256:9b3340f0c95fc33abe945b35e3d1e0520392dee5ea01c3f78f24cb65473fa242\",\n        \"bytes\": 17133,\n        \"description\": \"Frozen normative Specialist Run contract.\",\n        \"allowedWorkUnits\": [\n          \"fix.candidate-evidence-retention.r7\"\n        ],\n        \"readScope\": \"docs/specs/v12-ide-run-loop/evidence/implementation/release-correction-r7/inputs/specialist-run-contract.md\"\n      },\n      {\n        \"id\": \"context.test-plan\",\n        \"kind\": \"repository\",\n        \"locator\": \"path:docs/specs/v12-ide-run-loop/evidence/implementation/release-correction-r7/inputs/test-plan.md\",\n        \"digest\": \"sha256:ffa2102cbcf6d145d4f5b0ddbc26b9b02f86433a22b4b99b9f5cb084f605d7ec\",\n        \"bytes\": 2506,\n        \"description\": \"Frozen V12 verification obligations.\",\n        \"allowedWorkUnits\": [\n          \"fix.candidate-evidence-retention.r7\"\n        ],\n        \"readScope\": \"docs/specs/v12-ide-run-loop/evidence/implementation/release-correction-r7/inputs/test-plan.md\"\n      },\n      {\n        \"id\": \"context.v12-spec\",\n        \"kind\": \"repository\",\n        \"locator\": \"path:docs/specs/v12-ide-run-loop/evidence/implementation/release-correction-r7/inputs/spec.md\",\n        \"digest\": \"sha256:b0a3610c935cacf032e9c142d9436b6f620227667c64c5bf0e296eaf4f571ab1\",\n        \"bytes\": 5478,\n        \"description\": \"Frozen V12 feature specification.\",\n        \"allowedWorkUnits\": [\n          \"fix.candidate-evidence-retention.r7\"\n        ],\n        \"readScope\": \"docs/specs/v12-ide-run-loop/evidence/implementation/release-correction-r7/inputs/spec.md\"\n      }\n    ],\n    \"authority\": {\n      \"allowedModules\": [\n        \"correction.candidate-evidence-retention\"\n      ],\n      \"allowedCapabilities\": [\n        \"fix.candidate-evidence-retention\"\n      ],\n      \"permissionCeiling\": [\n        {\n          \"kind\": \"filesystem.read\",\n          \"scopes\": [\n            \".gitignore\",\n            \"docs/specs/v12-ide-run-loop/evidence/implementation/release-correction-r6/approval.json\",\n            \"docs/specs/v12-ide-run-loop/evidence/implementation/release-correction-r6/handoff-verification.json\",\n            \"docs/specs/v12-ide-run-loop/evidence/implementation/release-correction-r6/handoffs/agent.4a4cca8bce6a03e1f36dfd28b9505ff33920a045636f8715b10110fdbd408985.json\",\n            \"docs/specs/v12-ide-run-loop/evidence/implementation/release-correction-r6/handoffs/agent.9579818ca2843121c26d1c38b48b0f78421bcba0ed39783ced3bfd842a45904e.json\",\n            \"docs/specs/v12-ide-run-loop/evidence/implementation/release-correction-r6/package-envelope.json\",\n            \"docs/specs/v12-ide-run-loop/evidence/implementation/release-correction-r7/inputs/adr-0005.md\",\n            \"docs/specs/v12-ide-run-loop/evidence/implementation/release-correction-r7/inputs/spec.md\",\n            \"docs/specs/v12-ide-run-loop/evidence/implementation/release-correction-r7/inputs/specialist-run-contract.md\",\n            \"docs/specs/v12-ide-run-loop/evidence/implementation/release-correction-r7/inputs/test-plan.md\",\n            \"docs/specs/v12-ide-run-loop/evidence/release-review-r2/inputs/canonical-gate-receipt.json\",\n            \"docs/specs/v12-ide-run-loop/evidence/release-review-r2/inputs/canonical-gate.stderr.log\",\n            \"docs/specs/v12-ide-run-loop/evidence/release-review-r2/inputs/canonical-gate.stdout.log\",\n            \"docs/specs/v12-ide-run-loop/evidence/release-review-r2/run-release-review.mjs\",\n            \"docs/specs/v12-ide-run-loop/evidence/release-review-r2/verify-release-review-handoffs.mjs\",\n            \"package.json\",\n            \"scripts/run-v12-release-gate.mjs\"\n          ]\n        },\n        {\n          \"kind\": \"filesystem.write\",\n          \"scopes\": [\n            \".gitignore\",\n            \"docs/specs/v12-ide-run-loop/evidence/release-review-r2/run-release-review.mjs\",\n            \"scripts/run-v12-release-gate.mjs\"\n          ]\n        },\n        {\n          \"kind\": \"process.spawn\",\n          \"scopes\": [\n            \"git\",\n            \"node\",\n            \"npm\",\n            \"powershell\"\n          ]\n        }\n      ],\n      \"forbiddenEffects\": [\n        \"Do not use network access, change Git state, launch descendants, write outside the exact scope, or claim that core performs host effects.\"\n      ],\n      \"maxAgents\": 1,\n      \"maxConcurrency\": 1\n    },\n    \"optimization\": {\n      \"agentStartupCost\": 1,\n      \"handoffCost\": 1\n    },\n    \"workUnits\": [\n      {\n        \"id\": \"fix.candidate-evidence-retention.r7\",\n        \"objective\": \"Preserve exact canonical-gate raw evidence in Git without weakening the repository's general log-ignore policy.\",\n        \"weight\": 5,\n        \"module\": {\n          \"id\": \"correction.candidate-evidence-retention\",\n          \"action\": \"Add the narrowest durable ignore-policy exception for canonical-gate stdout and stderr evidence, then make the release-gate wrapper and R2 preparation/revalidation reject any required evidence path that Git still classifies as ignored.\",\n          \"inputPorts\": [\n            {\n              \"name\": \"input\",\n              \"artifactType\": \"IgnoredCanonicalGateEvidence\"\n            }\n          ],\n          \"outputPorts\": [\n            {\n              \"name\": \"output\",\n              \"artifactType\": \"VersionableCandidateBoundGateEvidence\"\n            }\n          ]\n        },\n        \"dependencies\": [],\n        \"requiredCapabilities\": [\n          \"fix.candidate-evidence-retention\"\n        ],\n        \"contextUses\": [\n          {\n            \"sourceId\": \"context.adr-0005\",\n            \"purpose\": \"Implement or verify the exact frozen V12 release-correction-r7 contract.\"\n          },\n          {\n            \"sourceId\": \"context.failed-gate-receipt\",\n            \"purpose\": \"Implement or verify the exact frozen V12 release-correction-r7 contract.\"\n          },\n          {\n            \"sourceId\": \"context.failed-gate-stderr\",\n            \"purpose\": \"Implement or verify the exact frozen V12 release-correction-r7 contract.\"\n          },\n          {\n            \"sourceId\": \"context.failed-gate-stdout\",\n            \"purpose\": \"Implement or verify the exact frozen V12 release-correction-r7 contract.\"\n          },\n          {\n            \"sourceId\": \"context.gitignore\",\n            \"purpose\": \"Implement or verify the exact frozen V12 release-correction-r7 contract.\"\n          },\n          {\n            \"sourceId\": \"context.package\",\n            \"purpose\": \"Implement or verify the exact frozen V12 release-correction-r7 contract.\"\n          },\n          {\n            \"sourceId\": \"context.release-correction-r6-approval\",\n            \"purpose\": \"Implement or verify the exact frozen V12 release-correction-r7 contract.\"\n          },\n          {\n            \"sourceId\": \"context.release-correction-r6-consumer-handoff\",\n            \"purpose\": \"Implement or verify the exact frozen V12 release-correction-r7 contract.\"\n          },\n          {\n            \"sourceId\": \"context.release-correction-r6-gate-handoff\",\n            \"purpose\": \"Implement or verify the exact frozen V12 release-correction-r7 contract.\"\n          },\n          {\n            \"sourceId\": \"context.release-correction-r6-package\",\n            \"purpose\": \"Implement or verify the exact frozen V12 release-correction-r7 contract.\"\n          },\n          {\n            \"sourceId\": \"context.release-correction-r6-report\",\n            \"purpose\": \"Implement or verify the exact frozen V12 release-correction-r7 contract.\"\n          },\n          {\n            \"sourceId\": \"context.release-gate\",\n            \"purpose\": \"Implement or verify the exact frozen V12 release-correction-r7 contract.\"\n          },\n          {\n            \"sourceId\": \"context.release-review-r2-harness\",\n            \"purpose\": \"Implement or verify the exact frozen V12 release-correction-r7 contract.\"\n          },\n          {\n            \"sourceId\": \"context.release-review-r2-verifier\",\n            \"purpose\": \"Implement or verify the exact frozen V12 release-correction-r7 contract.\"\n          },\n          {\n            \"sourceId\": \"context.run-contract\",\n            \"purpose\": \"Implement or verify the exact frozen V12 release-correction-r7 contract.\"\n          },\n          {\n            \"sourceId\": \"context.test-plan\",\n            \"purpose\": \"Implement or verify the exact frozen V12 release-correction-r7 contract.\"\n          },\n          {\n            \"sourceId\": \"context.v12-spec\",\n            \"purpose\": \"Implement or verify the exact frozen V12 release-correction-r7 contract.\"\n          }\n        ],\n        \"scope\": {\n          \"read\": [\n            \".gitignore\",\n            \"docs/specs/v12-ide-run-loop/evidence/implementation/release-correction-r6/approval.json\",\n            \"docs/specs/v12-ide-run-loop/evidence/implementation/release-correction-r6/handoff-verification.json\",\n            \"docs/specs/v12-ide-run-loop/evidence/implementation/release-correction-r6/handoffs/agent.4a4cca8bce6a03e1f36dfd28b9505ff33920a045636f8715b10110fdbd408985.json\",\n            \"docs/specs/v12-ide-run-loop/evidence/implementation/release-correction-r6/handoffs/agent.9579818ca2843121c26d1c38b48b0f78421bcba0ed39783ced3bfd842a45904e.json\",\n            \"docs/specs/v12-ide-run-loop/evidence/implementation/release-correction-r6/package-envelope.json\",\n            \"docs/specs/v12-ide-run-loop/evidence/implementation/release-correction-r7/inputs/adr-0005.md\",\n            \"docs/specs/v12-ide-run-loop/evidence/implementation/release-correction-r7/inputs/spec.md\",\n            \"docs/specs/v12-ide-run-loop/evidence/implementation/release-correction-r7/inputs/specialist-run-contract.md\",\n            \"docs/specs/v12-ide-run-loop/evidence/implementation/release-correction-r7/inputs/test-plan.md\",\n            \"docs/specs/v12-ide-run-loop/evidence/release-review-r2/inputs/canonical-gate-receipt.json\",\n            \"docs/specs/v12-ide-run-loop/evidence/release-review-r2/inputs/canonical-gate.stderr.log\",\n            \"docs/specs/v12-ide-run-loop/evidence/release-review-r2/inputs/canonical-gate.stdout.log\",\n            \"docs/specs/v12-ide-run-loop/evidence/release-review-r2/run-release-review.mjs\",\n            \"docs/specs/v12-ide-run-loop/evidence/release-review-r2/verify-release-review-handoffs.mjs\",\n            \"package.json\",\n            \"scripts/run-v12-release-gate.mjs\"\n          ],\n          \"write\": [\n            \".gitignore\",\n            \"docs/specs/v12-ide-run-loop/evidence/release-review-r2/run-release-review.mjs\",\n            \"scripts/run-v12-release-gate.mjs\"\n          ],\n          \"conflictZones\": [\n            \".gitignore\",\n            \"docs/specs/v12-ide-run-loop/evidence/release-review-r2/run-release-review.mjs\",\n            \"scripts/run-v12-release-gate.mjs\"\n          ]\n        },\n        \"permissions\": [\n          {\n            \"kind\": \"filesystem.read\",\n            \"scopes\": [\n              \".gitignore\",\n              \"docs/specs/v12-ide-run-loop/evidence/implementation/release-correction-r6/approval.json\",\n              \"docs/specs/v12-ide-run-loop/evidence/implementation/release-correction-r6/handoff-verification.json\",\n              \"docs/specs/v12-ide-run-loop/evidence/implementation/release-correction-r6/handoffs/agent.4a4cca8bce6a03e1f36dfd28b9505ff33920a045636f8715b10110fdbd408985.json\",\n              \"docs/specs/v12-ide-run-loop/evidence/implementation/release-correction-r6/handoffs/agent.9579818ca2843121c26d1c38b48b0f78421bcba0ed39783ced3bfd842a45904e.json\",\n              \"docs/specs/v12-ide-run-loop/evidence/implementation/release-correction-r6/package-envelope.json\",\n              \"docs/specs/v12-ide-run-loop/evidence/implementation/release-correction-r7/inputs/adr-0005.md\",\n              \"docs/specs/v12-ide-run-loop/evidence/implementation/release-correction-r7/inputs/spec.md\",\n              \"docs/specs/v12-ide-run-loop/evidence/implementation/release-correction-r7/inputs/specialist-run-contract.md\",\n              \"docs/specs/v12-ide-run-loop/evidence/implementation/release-correction-r7/inputs/test-plan.md\",\n              \"docs/specs/v12-ide-run-loop/evidence/release-review-r2/inputs/canonical-gate-receipt.json\",\n              \"docs/specs/v12-ide-run-loop/evidence/release-review-r2/inputs/canonical-gate.stderr.log\",\n              \"docs/specs/v12-ide-run-loop/evidence/release-review-r2/inputs/canonical-gate.stdout.log\",\n              \"docs/specs/v12-ide-run-loop/evidence/release-review-r2/run-release-review.mjs\",\n              \"docs/specs/v12-ide-run-loop/evidence/release-review-r2/verify-release-review-handoffs.mjs\",\n              \"package.json\",\n              \"scripts/run-v12-release-gate.mjs\"\n            ]\n          },\n          {\n            \"kind\": \"filesystem.write\",\n            \"scopes\": [\n              \".gitignore\",\n              \"docs/specs/v12-ide-run-loop/evidence/release-review-r2/run-release-review.mjs\",\n              \"scripts/run-v12-release-gate.mjs\"\n            ]\n          },\n          {\n            \"kind\": \"process.spawn\",\n            \"scopes\": [\n              \"git\",\n              \"node\",\n              \"npm\",\n              \"powershell\"\n            ]\n          }\n        ],\n        \"evidenceRequirementIds\": [\n          \"evidence.candidate-evidence-retention.r7\"\n        ],\n        \"handoffArtifacts\": [\n          \"candidate-evidence-retention-correction-r7.md\"\n        ],\n        \"stopConditions\": [\n          \"If native apply_patch fails before mutation because of the host sandbox, an exact precondition-hash-guarded PowerShell write is allowed within the declared write scope; verify the resulting file bytes immediately.\",\n          \"Return only the concrete closed SpecialistAgentHandoff JSON shape from the generated contract.\",\n          \"Run only local focused verification allowed by the contract and report every failing command truthfully.\",\n          \"Stop if any declared source is unavailable or fails its exact digest and byte binding.\",\n          \"Write only the exact declared write scope; do not change Git state, use the network, launch descendants, or widen the public contract.\"\n        ]\n      }\n    ]\n  },\n  \"goalDigest\": \"sha256:4513970fcccbc4be4173c848fd72bf4b76a4ee52ccc4ae739105d2ffcc30248b\",\n  \"proposedCandidates\": [],\n  \"proposalEvaluations\": [],\n  \"authority\": {\n    \"apiVersion\": \"swecircuit/specialist/v1alpha1\",\n    \"kind\": \"TaskAuthorityProjection\",\n    \"goalId\": \"v12.ide-run-loop.implementation.release-correction\",\n    \"goalRevision\": 7,\n    \"allowedModules\": [\n      \"correction.candidate-evidence-retention\"\n    ],\n    \"allowedCapabilities\": [\n      \"fix.candidate-evidence-retention\"\n    ],\n    \"contextSources\": [\n      {\n        \"id\": \"context.adr-0005\",\n        \"kind\": \"repository\",\n        \"locator\": \"path:docs/specs/v12-ide-run-loop/evidence/implementation/release-correction-r7/inputs/adr-0005.md\",\n        \"digest\": \"sha256:bb585b88635787a7f835e5eb503f6e0053bed624db13b21e9a769d8a5e619b14\",\n        \"bytes\": 9031,\n        \"description\": \"Accepted immutable Specialist Run Session decision.\",\n        \"allowedWorkUnits\": [\n          \"fix.candidate-evidence-retention.r7\"\n        ],\n        \"readScope\": \"docs/specs/v12-ide-run-loop/evidence/implementation/release-correction-r7/inputs/adr-0005.md\"\n      },\n      {\n        \"id\": \"context.failed-gate-receipt\",\n        \"kind\": \"repository\",\n        \"locator\": \"path:docs/specs/v12-ide-run-loop/evidence/release-review-r2/inputs/canonical-gate-receipt.json\",\n        \"digest\": \"sha256:4c636e486f36c22b74f12fdd4b4470eb9056f63f64eca05058ae6923976bb15c\",\n        \"bytes\": 1221,\n        \"description\": \"Immutable candidate-1 canonical-gate failure receipt.\",\n        \"allowedWorkUnits\": [\n          \"fix.candidate-evidence-retention.r7\"\n        ],\n        \"readScope\": \"docs/specs/v12-ide-run-loop/evidence/release-review-r2/inputs/canonical-gate-receipt.json\"\n      },\n      {\n        \"id\": \"context.failed-gate-stderr\",\n        \"kind\": \"repository\",\n        \"locator\": \"path:docs/specs/v12-ide-run-loop/evidence/release-review-r2/inputs/canonical-gate.stderr.log\",\n        \"digest\": \"sha256:4381d1a9ce1c36beb8723eadfb3619288935b9d095de672c450121c23dc0dfad\",\n        \"bytes\": 11763,\n        \"description\": \"Exact raw candidate-1 canonical-gate stderr bytes.\",\n        \"allowedWorkUnits\": [\n          \"fix.candidate-evidence-retention.r7\"\n        ],\n        \"readScope\": \"docs/specs/v12-ide-run-loop/evidence/release-review-r2/inputs/canonical-gate.stderr.log\"\n      },\n      {\n        \"id\": \"context.failed-gate-stdout\",\n        \"kind\": \"repository\",\n        \"locator\": \"path:docs/specs/v12-ide-run-loop/evidence/release-review-r2/inputs/canonical-gate.stdout.log\",\n        \"digest\": \"sha256:afb6b266dd504cbf89d2cb55b6f9c5c6872fd5636acef8848e2105257aecef12\",\n        \"bytes\": 295768,\n        \"description\": \"Exact raw candidate-1 canonical-gate stdout bytes.\",\n        \"allowedWorkUnits\": [\n          \"fix.candidate-evidence-retention.r7\"\n        ],\n        \"readScope\": \"docs/specs/v12-ide-run-loop/evidence/release-review-r2/inputs/canonical-gate.stdout.log\"\n      },\n      {\n        \"id\": \"context.gitignore\",\n        \"kind\": \"repository\",\n        \"locator\": \"path:.gitignore\",\n        \"digest\": \"sha256:ad4ce9d55303f62f262e18b7e47710d9e43049625c704cbaa46cbb4487bbc8d8\",\n        \"bytes\": 340,\n        \"description\": \"Repository ignore policy that currently suppresses canonical-gate raw log evidence.\",\n        \"allowedWorkUnits\": [\n          \"fix.candidate-evidence-retention.r7\"\n        ],\n        \"readScope\": \".gitignore\"\n      },\n      {\n        \"id\": \"context.package\",\n        \"kind\": \"repository\",\n        \"locator\": \"path:package.json\",\n        \"digest\": \"sha256:43414ace7e294a9a173ee78ab33baa5791959921f5da2a1c7b3b69d081938df2\",\n        \"bytes\": 2946,\n        \"description\": \"Existing package scripts and export map.\",\n        \"allowedWorkUnits\": [\n          \"fix.candidate-evidence-retention.r7\"\n        ],\n        \"readScope\": \"package.json\"\n      },\n      {\n        \"id\": \"context.release-correction-r6-approval\",\n        \"kind\": \"repository\",\n        \"locator\": \"path:docs/specs/v12-ide-run-loop/evidence/implementation/release-correction-r6/approval.json\",\n        \"digest\": \"sha256:b0a48bde829f601ec4d11abeb5c0f54dcb7123182d2c1fbdb405fc251b28a27c\",\n        \"bytes\": 641,\n        \"description\": \"Exact owner approval for the revision-6 package.\",\n        \"allowedWorkUnits\": [\n          \"fix.candidate-evidence-retention.r7\"\n        ],\n        \"readScope\": \"docs/specs/v12-ide-run-loop/evidence/implementation/release-correction-r6/approval.json\"\n      },\n      {\n        \"id\": \"context.release-correction-r6-consumer-handoff\",\n        \"kind\": \"repository\",\n        \"locator\": \"path:docs/specs/v12-ide-run-loop/evidence/implementation/release-correction-r6/handoffs/agent.9579818ca2843121c26d1c38b48b0f78421bcba0ed39783ced3bfd842a45904e.json\",\n        \"digest\": \"sha256:939099add2852e3dfe14b307fc55e46c89b56a1dd0c735d15bf35e82f99a5a68\",\n        \"bytes\": 5291,\n        \"description\": \"Exact revision-6 consumer and architecture parity PASS handoff.\",\n        \"allowedWorkUnits\": [\n          \"fix.candidate-evidence-retention.r7\"\n        ],\n        \"readScope\": \"docs/specs/v12-ide-run-loop/evidence/implementation/release-correction-r6/handoffs/agent.9579818ca2843121c26d1c38b48b0f78421bcba0ed39783ced3bfd842a45904e.json\"\n      },\n      {\n        \"id\": \"context.release-correction-r6-gate-handoff\",\n        \"kind\": \"repository\",\n        \"locator\": \"path:docs/specs/v12-ide-run-loop/evidence/implementation/release-correction-r6/handoffs/agent.4a4cca8bce6a03e1f36dfd28b9505ff33920a045636f8715b10110fdbd408985.json\",\n        \"digest\": \"sha256:3c95ca87255613bdcb96f0a894a03ce012c4d5662a3379230c07166e56fcf33b\",\n        \"bytes\": 5061,\n        \"description\": \"Exact revision-6 candidate-gate identity PASS handoff.\",\n        \"allowedWorkUnits\": [\n          \"fix.candidate-evidence-retention.r7\"\n        ],\n        \"readScope\": \"docs/specs/v12-ide-run-loop/evidence/implementation/release-correction-r6/handoffs/agent.4a4cca8bce6a03e1f36dfd28b9505ff33920a045636f8715b10110fdbd408985.json\"\n      },\n      {\n        \"id\": \"context.release-correction-r6-package\",\n        \"kind\": \"repository\",\n        \"locator\": \"path:docs/specs/v12-ide-run-loop/evidence/implementation/release-correction-r6/package-envelope.json\",\n        \"digest\": \"sha256:08fba946e7d8fd47b112322a4f8ea954922d230de6d2b9fac234bdd297f6540f\",\n        \"bytes\": 152251,\n        \"description\": \"Owner-approved revision-6 consumer-parity and candidate-identity package.\",\n        \"allowedWorkUnits\": [\n          \"fix.candidate-evidence-retention.r7\"\n        ],\n        \"readScope\": \"docs/specs/v12-ide-run-loop/evidence/implementation/release-correction-r6/package-envelope.json\"\n      },\n      {\n        \"id\": \"context.release-correction-r6-report\",\n        \"kind\": \"repository\",\n        \"locator\": \"path:docs/specs/v12-ide-run-loop/evidence/implementation/release-correction-r6/handoff-verification.json\",\n        \"digest\": \"sha256:3d3a406acd342a7c32d22e7cd3a92a0c7db89d74af50d9d394da9a93830c76fb\",\n        \"bytes\": 1998,\n        \"description\": \"Complete revision-6 PASS handoff report.\",\n        \"allowedWorkUnits\": [\n          \"fix.candidate-evidence-retention.r7\"\n        ],\n        \"readScope\": \"docs/specs/v12-ide-run-loop/evidence/implementation/release-correction-r6/handoff-verification.json\"\n      },\n      {\n        \"id\": \"context.release-gate\",\n        \"kind\": \"repository\",\n        \"locator\": \"path:scripts/run-v12-release-gate.mjs\",\n        \"digest\": \"sha256:552d8a11ed3f05156b935e9f461083ac9e1f00897bc797a0d3fe7c7a7d25822b\",\n        \"bytes\": 6999,\n        \"description\": \"Current candidate-bound canonical gate wrapper.\",\n        \"allowedWorkUnits\": [\n          \"fix.candidate-evidence-retention.r7\"\n        ],\n        \"readScope\": \"scripts/run-v12-release-gate.mjs\"\n      },\n      {\n        \"id\": \"context.release-review-r2-harness\",\n        \"kind\": \"repository\",\n        \"locator\": \"path:docs/specs/v12-ide-run-loop/evidence/release-review-r2/run-release-review.mjs\",\n        \"digest\": \"sha256:b41e59d7cf5d905a088c7445f7ede71019be8a15aa17273fe216a60af8fc149c\",\n        \"bytes\": 66496,\n        \"description\": \"Current candidate-bound R2 release-review preparation and compilation harness.\",\n        \"allowedWorkUnits\": [\n          \"fix.candidate-evidence-retention.r7\"\n        ],\n        \"readScope\": \"docs/specs/v12-ide-run-loop/evidence/release-review-r2/run-release-review.mjs\"\n      },\n      {\n        \"id\": \"context.release-review-r2-verifier\",\n        \"kind\": \"repository\",\n        \"locator\": \"path:docs/specs/v12-ide-run-loop/evidence/release-review-r2/verify-release-review-handoffs.mjs\",\n        \"digest\": \"sha256:e30bbf7548d6481935d14db57630e4e5bdaa9aff2df56337b957d07acc83d2aa\",\n        \"bytes\": 6984,\n        \"description\": \"Current exact R2 reviewer handoff verifier.\",\n        \"allowedWorkUnits\": [\n          \"fix.candidate-evidence-retention.r7\"\n        ],\n        \"readScope\": \"docs/specs/v12-ide-run-loop/evidence/release-review-r2/verify-release-review-handoffs.mjs\"\n      },\n      {\n        \"id\": \"context.run-contract\",\n        \"kind\": \"repository\",\n        \"locator\": \"path:docs/specs/v12-ide-run-loop/evidence/implementation/release-correction-r7/inputs/specialist-run-contract.md\",\n        \"digest\": \"sha256:9b3340f0c95fc33abe945b35e3d1e0520392dee5ea01c3f78f24cb65473fa242\",\n        \"bytes\": 17133,\n        \"description\": \"Frozen normative Specialist Run contract.\",\n        \"allowedWorkUnits\": [\n          \"fix.candidate-evidence-retention.r7\"\n        ],\n        \"readScope\": \"docs/specs/v12-ide-run-loop/evidence/implementation/release-correction-r7/inputs/specialist-run-contract.md\"\n      },\n      {\n        \"id\": \"context.test-plan\",\n        \"kind\": \"repository\",\n        \"locator\": \"path:docs/specs/v12-ide-run-loop/evidence/implementation/release-correction-r7/inputs/test-plan.md\",\n        \"digest\": \"sha256:ffa2102cbcf6d145d4f5b0ddbc26b9b02f86433a22b4b99b9f5cb084f605d7ec\",\n        \"bytes\": 2506,\n        \"description\": \"Frozen V12 verification obligations.\",\n        \"allowedWorkUnits\": [\n          \"fix.candidate-evidence-retention.r7\"\n        ],\n        \"readScope\": \"docs/specs/v12-ide-run-loop/evidence/implementation/release-correction-r7/inputs/test-plan.md\"\n      },\n      {\n        \"id\": \"context.v12-spec\",\n        \"kind\": \"repository\",\n        \"locator\": \"path:docs/specs/v12-ide-run-loop/evidence/implementation/release-correction-r7/inputs/spec.md\",\n        \"digest\": \"sha256:b0a3610c935cacf032e9c142d9436b6f620227667c64c5bf0e296eaf4f571ab1\",\n        \"bytes\": 5478,\n        \"description\": \"Frozen V12 feature specification.\",\n        \"allowedWorkUnits\": [\n          \"fix.candidate-evidence-retention.r7\"\n        ],\n        \"readScope\": \"docs/specs/v12-ide-run-loop/evidence/implementation/release-correction-r7/inputs/spec.md\"\n      }\n    ],\n    \"permissionCeiling\": [\n      {\n        \"kind\": \"filesystem.read\",\n        \"scopes\": [\n          \".gitignore\",\n          \"docs/specs/v12-ide-run-loop/evidence/implementation/release-correction-r6/approval.json\",\n          \"docs/specs/v12-ide-run-loop/evidence/implementation/release-correction-r6/handoff-verification.json\",\n          \"docs/specs/v12-ide-run-loop/evidence/implementation/release-correction-r6/handoffs/agent.4a4cca8bce6a03e1f36dfd28b9505ff33920a045636f8715b10110fdbd408985.json\",\n          \"docs/specs/v12-ide-run-loop/evidence/implementation/release-correction-r6/handoffs/agent.9579818ca2843121c26d1c38b48b0f78421bcba0ed39783ced3bfd842a45904e.json\",\n          \"docs/specs/v12-ide-run-loop/evidence/implementation/release-correction-r6/package-envelope.json\",\n          \"docs/specs/v12-ide-run-loop/evidence/implementation/release-correction-r7/inputs/adr-0005.md\",\n          \"docs/specs/v12-ide-run-loop/evidence/implementation/release-correction-r7/inputs/spec.md\",\n          \"docs/specs/v12-ide-run-loop/evidence/implementation/release-correction-r7/inputs/specialist-run-contract.md\",\n          \"docs/specs/v12-ide-run-loop/evidence/implementation/release-correction-r7/inputs/test-plan.md\",\n          \"docs/specs/v12-ide-run-loop/evidence/release-review-r2/inputs/canonical-gate-receipt.json\",\n          \"docs/specs/v12-ide-run-loop/evidence/release-review-r2/inputs/canonical-gate.stderr.log\",\n          \"docs/specs/v12-ide-run-loop/evidence/release-review-r2/inputs/canonical-gate.stdout.log\",\n          \"docs/specs/v12-ide-run-loop/evidence/release-review-r2/run-release-review.mjs\",\n          \"docs/specs/v12-ide-run-loop/evidence/release-review-r2/verify-release-review-handoffs.mjs\",\n          \"package.json\",\n          \"scripts/run-v12-release-gate.mjs\"\n        ]\n      },\n      {\n        \"kind\": \"filesystem.write\",\n        \"scopes\": [\n          \".gitignore\",\n          \"docs/specs/v12-ide-run-loop/evidence/release-review-r2/run-release-review.mjs\",\n          \"scripts/run-v12-release-gate.mjs\"\n        ]\n      },\n      {\n        \"kind\": \"process.spawn\",\n        \"scopes\": [\n          \"git\",\n          \"node\",\n          \"npm\",\n          \"powershell\"\n        ]\n      }\n    ],\n    \"forbiddenEffects\": [\n      \"Do not use network access, change Git state, launch descendants, write outside the exact scope, or claim that core performs host effects.\"\n    ],\n    \"maxAgents\": 1,\n    \"maxConcurrency\": 1,\n    \"contentDigest\": \"sha256:de6701b8d15d646167f03fa4ab1761a858b720814097a67149191d635dfb5198\"\n  },\n  \"search\": {\n    \"mode\": \"exact\",\n    \"claim\": \"exhaustive_partition_search_fixed_scheduler\",\n    \"workUnitCount\": 1,\n    \"evaluatedCandidates\": 1,\n    \"eligibleCandidates\": 1,\n    \"retainedAlternatives\": 0,\n    \"evaluationSetDigest\": \"sha256:2e0b8eb5d4b9f9df75b71e3419222e94574d904823f6154d2626c5839705fe2f\"\n  },\n  \"serialBaseline\": {\n    \"id\": \"team.95637f6ac2bb74c533055e0666c20a7824db48103f5998e8831bdfedc23284e9\",\n    \"partition\": [\n      [\n        \"fix.candidate-evidence-retention.r7\"\n      ]\n    ],\n    \"origins\": [\n      \"serial_baseline\",\n      \"exact_search\"\n    ],\n    \"proposalIds\": [],\n    \"eligible\": true,\n    \"rejectionCodes\": [],\n    \"metrics\": {\n      \"agentCount\": 1,\n      \"projectedMakespan\": 6,\n      \"peakConcurrency\": 1,\n      \"conflictPairs\": 0,\n      \"handoffCount\": 0,\n      \"duplicatedContextBytes\": 0,\n      \"duplicatedPermissionScopes\": 0,\n      \"totalWorkWeight\": 5,\n      \"totalStartupCost\": 1,\n      \"totalHandoffCost\": 0\n    },\n    \"schedule\": [\n      {\n        \"agentId\": \"agent.5f16c5677b283cd8f5c13655b4b07216731fd3fdb5dfba7c6112471d5bd55c7c\",\n        \"start\": 0,\n        \"finish\": 6\n      }\n    ],\n    \"contentDigest\": \"sha256:f94cfd212776cddc362b781df9db22af33b25c35783b5fc92f94b3553137c5ae\"\n  },\n  \"selected\": {\n    \"id\": \"team.95637f6ac2bb74c533055e0666c20a7824db48103f5998e8831bdfedc23284e9\",\n    \"partition\": [\n      [\n        \"fix.candidate-evidence-retention.r7\"\n      ]\n    ],\n    \"origins\": [\n      \"serial_baseline\",\n      \"exact_search\"\n    ],\n    \"proposalIds\": [],\n    \"eligible\": true,\n    \"rejectionCodes\": [],\n    \"metrics\": {\n      \"agentCount\": 1,\n      \"projectedMakespan\": 6,\n      \"peakConcurrency\": 1,\n      \"conflictPairs\": 0,\n      \"handoffCount\": 0,\n      \"duplicatedContextBytes\": 0,\n      \"duplicatedPermissionScopes\": 0,\n      \"totalWorkWeight\": 5,\n      \"totalStartupCost\": 1,\n      \"totalHandoffCost\": 0\n    },\n    \"schedule\": [\n      {\n        \"agentId\": \"agent.5f16c5677b283cd8f5c13655b4b07216731fd3fdb5dfba7c6112471d5bd55c7c\",\n        \"start\": 0,\n        \"finish\": 6\n      }\n    ],\n    \"contentDigest\": \"sha256:f94cfd212776cddc362b781df9db22af33b25c35783b5fc92f94b3553137c5ae\"\n  },\n  \"selectionReason\": {\n    \"kind\": \"serial_selected\",\n    \"decisiveField\": \"serial_baseline\",\n    \"selectedValue\": \"team.95637f6ac2bb74c533055e0666c20a7824db48103f5998e8831bdfedc23284e9\",\n    \"serialValue\": \"team.95637f6ac2bb74c533055e0666c20a7824db48103f5998e8831bdfedc23284e9\",\n    \"serialRejectionCodes\": []\n  },\n  \"alternatives\": [],\n  \"blueprints\": [\n    {\n      \"apiVersion\": \"swecircuit/specialist/v1alpha1\",\n      \"kind\": \"AgentBlueprint\",\n      \"id\": \"agent.5f16c5677b283cd8f5c13655b4b07216731fd3fdb5dfba7c6112471d5bd55c7c\",\n      \"goalId\": \"v12.ide-run-loop.implementation.release-correction\",\n      \"goalRevision\": 7,\n      \"goalDigest\": \"sha256:4513970fcccbc4be4173c848fd72bf4b76a4ee52ccc4ae739105d2ffcc30248b\",\n      \"candidateId\": \"team.95637f6ac2bb74c533055e0666c20a7824db48103f5998e8831bdfedc23284e9\",\n      \"workUnitIds\": [\n        \"fix.candidate-evidence-retention.r7\"\n      ],\n      \"objectives\": [\n        {\n          \"workUnitId\": \"fix.candidate-evidence-retention.r7\",\n          \"objective\": \"Preserve exact canonical-gate raw evidence in Git without weakening the repository's general log-ignore policy.\"\n        }\n      ],\n      \"modules\": [\n        {\n          \"id\": \"correction.candidate-evidence-retention\",\n          \"action\": \"Add the narrowest durable ignore-policy exception for canonical-gate stdout and stderr evidence, then make the release-gate wrapper and R2 preparation/revalidation reject any required evidence path that Git still classifies as ignored.\",\n          \"inputPorts\": [\n            {\n              \"name\": \"input\",\n              \"artifactType\": \"IgnoredCanonicalGateEvidence\"\n            }\n          ],\n          \"outputPorts\": [\n            {\n              \"name\": \"output\",\n              \"artifactType\": \"VersionableCandidateBoundGateEvidence\"\n            }\n          ]\n        }\n      ],\n      \"dependencies\": [],\n      \"contextUses\": [\n        {\n          \"sourceId\": \"context.adr-0005\",\n          \"kind\": \"repository\",\n          \"locator\": \"path:docs/specs/v12-ide-run-loop/evidence/implementation/release-correction-r7/inputs/adr-0005.md\",\n          \"digest\": \"sha256:bb585b88635787a7f835e5eb503f6e0053bed624db13b21e9a769d8a5e619b14\",\n          \"bytes\": 9031,\n          \"purposes\": [\n            \"Implement or verify the exact frozen V12 release-correction-r7 contract.\"\n          ],\n          \"workUnitIds\": [\n            \"fix.candidate-evidence-retention.r7\"\n          ],\n          \"readScope\": \"docs/specs/v12-ide-run-loop/evidence/implementation/release-correction-r7/inputs/adr-0005.md\"\n        },\n        {\n          \"sourceId\": \"context.failed-gate-receipt\",\n          \"kind\": \"repository\",\n          \"locator\": \"path:docs/specs/v12-ide-run-loop/evidence/release-review-r2/inputs/canonical-gate-receipt.json\",\n          \"digest\": \"sha256:4c636e486f36c22b74f12fdd4b4470eb9056f63f64eca05058ae6923976bb15c\",\n          \"bytes\": 1221,\n          \"purposes\": [\n            \"Implement or verify the exact frozen V12 release-correction-r7 contract.\"\n          ],\n          \"workUnitIds\": [\n            \"fix.candidate-evidence-retention.r7\"\n          ],\n          \"readScope\": \"docs/specs/v12-ide-run-loop/evidence/release-review-r2/inputs/canonical-gate-receipt.json\"\n        },\n        {\n          \"sourceId\": \"context.failed-gate-stderr\",\n          \"kind\": \"repository\",\n          \"locator\": \"path:docs/specs/v12-ide-run-loop/evidence/release-review-r2/inputs/canonical-gate.stderr.log\",\n          \"digest\": \"sha256:4381d1a9ce1c36beb8723eadfb3619288935b9d095de672c450121c23dc0dfad\",\n          \"bytes\": 11763,\n          \"purposes\": [\n            \"Implement or verify the exact frozen V12 release-correction-r7 contract.\"\n          ],\n          \"workUnitIds\": [\n            \"fix.candidate-evidence-retention.r7\"\n          ],\n          \"readScope\": \"docs/specs/v12-ide-run-loop/evidence/release-review-r2/inputs/canonical-gate.stderr.log\"\n        },\n        {\n          \"sourceId\": \"context.failed-gate-stdout\",\n          \"kind\": \"repository\",\n          \"locator\": \"path:docs/specs/v12-ide-run-loop/evidence/release-review-r2/inputs/canonical-gate.stdout.log\",\n          \"digest\": \"sha256:afb6b266dd504cbf89d2cb55b6f9c5c6872fd5636acef8848e2105257aecef12\",\n          \"bytes\": 295768,\n          \"purposes\": [\n            \"Implement or verify the exact frozen V12 release-correction-r7 contract.\"\n          ],\n          \"workUnitIds\": [\n            \"fix.candidate-evidence-retention.r7\"\n          ],\n          \"readScope\": \"docs/specs/v12-ide-run-loop/evidence/release-review-r2/inputs/canonical-gate.stdout.log\"\n        },\n        {\n          \"sourceId\": \"context.gitignore\",\n          \"kind\": \"repository\",\n          \"locator\": \"path:.gitignore\",\n          \"digest\": \"sha256:ad4ce9d55303f62f262e18b7e47710d9e43049625c704cbaa46cbb4487bbc8d8\",\n          \"bytes\": 340,\n          \"purposes\": [\n            \"Implement or verify the exact frozen V12 release-correction-r7 contract.\"\n          ],\n          \"workUnitIds\": [\n            \"fix.candidate-evidence-retention.r7\"\n          ],\n          \"readScope\": \".gitignore\"\n        },\n        {\n          \"sourceId\": \"context.package\",\n          \"kind\": \"repository\",\n          \"locator\": \"path:package.json\",\n          \"digest\": \"sha256:43414ace7e294a9a173ee78ab33baa5791959921f5da2a1c7b3b69d081938df2\",\n          \"bytes\": 2946,\n          \"purposes\": [\n            \"Implement or verify the exact frozen V12 release-correction-r7 contract.\"\n          ],\n          \"workUnitIds\": [\n            \"fix.candidate-evidence-retention.r7\"\n          ],\n          \"readScope\": \"package.json\"\n        },\n        {\n          \"sourceId\": \"context.release-correction-r6-approval\",\n          \"kind\": \"repository\",\n          \"locator\": \"path:docs/specs/v12-ide-run-loop/evidence/implementation/release-correction-r6/approval.json\",\n          \"digest\": \"sha256:b0a48bde829f601ec4d11abeb5c0f54dcb7123182d2c1fbdb405fc251b28a27c\",\n          \"bytes\": 641,\n          \"purposes\": [\n            \"Implement or verify the exact frozen V12 release-correction-r7 contract.\"\n          ],\n          \"workUnitIds\": [\n            \"fix.candidate-evidence-retention.r7\"\n          ],\n          \"readScope\": \"docs/specs/v12-ide-run-loop/evidence/implementation/release-correction-r6/approval.json\"\n        },\n        {\n          \"sourceId\": \"context.release-correction-r6-consumer-handoff\",\n          \"kind\": \"repository\",\n          \"locator\": \"path:docs/specs/v12-ide-run-loop/evidence/implementation/release-correction-r6/handoffs/agent.9579818ca2843121c26d1c38b48b0f78421bcba0ed39783ced3bfd842a45904e.json\",\n          \"digest\": \"sha256:939099add2852e3dfe14b307fc55e46c89b56a1dd0c735d15bf35e82f99a5a68\",\n          \"bytes\": 5291,\n          \"purposes\": [\n            \"Implement or verify the exact frozen V12 release-correction-r7 contract.\"\n          ],\n          \"workUnitIds\": [\n            \"fix.candidate-evidence-retention.r7\"\n          ],\n          \"readScope\": \"docs/specs/v12-ide-run-loop/evidence/implementation/release-correction-r6/handoffs/agent.9579818ca2843121c26d1c38b48b0f78421bcba0ed39783ced3bfd842a45904e.json\"\n        },\n        {\n          \"sourceId\": \"context.release-correction-r6-gate-handoff\",\n          \"kind\": \"repository\",\n          \"locator\": \"path:docs/specs/v12-ide-run-loop/evidence/implementation/release-correction-r6/handoffs/agent.4a4cca8bce6a03e1f36dfd28b9505ff33920a045636f8715b10110fdbd408985.json\",\n          \"digest\": \"sha256:3c95ca87255613bdcb96f0a894a03ce012c4d5662a3379230c07166e56fcf33b\",\n          \"bytes\": 5061,\n          \"purposes\": [\n            \"Implement or verify the exact frozen V12 release-correction-r7 contract.\"\n          ],\n          \"workUnitIds\": [\n            \"fix.candidate-evidence-retention.r7\"\n          ],\n          \"readScope\": \"docs/specs/v12-ide-run-loop/evidence/implementation/release-correction-r6/handoffs/agent.4a4cca8bce6a03e1f36dfd28b9505ff33920a045636f8715b10110fdbd408985.json\"\n        },\n        {\n          \"sourceId\": \"context.release-correction-r6-package\",\n          \"kind\": \"repository\",\n          \"locator\": \"path:docs/specs/v12-ide-run-loop/evidence/implementation/release-correction-r6/package-envelope.json\",\n          \"digest\": \"sha256:08fba946e7d8fd47b112322a4f8ea954922d230de6d2b9fac234bdd297f6540f\",\n          \"bytes\": 152251,\n          \"purposes\": [\n            \"Implement or verify the exact frozen V12 release-correction-r7 contract.\"\n          ],\n          \"workUnitIds\": [\n            \"fix.candidate-evidence-retention.r7\"\n          ],\n          \"readScope\": \"docs/specs/v12-ide-run-loop/evidence/implementation/release-correction-r6/package-envelope.json\"\n        },\n        {\n          \"sourceId\": \"context.release-correction-r6-report\",\n          \"kind\": \"repository\",\n          \"locator\": \"path:docs/specs/v12-ide-run-loop/evidence/implementation/release-correction-r6/handoff-verification.json\",\n          \"digest\": \"sha256:3d3a406acd342a7c32d22e7cd3a92a0c7db89d74af50d9d394da9a93830c76fb\",\n          \"bytes\": 1998,\n          \"purposes\": [\n            \"Implement or verify the exact frozen V12 release-correction-r7 contract.\"\n          ],\n          \"workUnitIds\": [\n            \"fix.candidate-evidence-retention.r7\"\n          ],\n          \"readScope\": \"docs/specs/v12-ide-run-loop/evidence/implementation/release-correction-r6/handoff-verification.json\"\n        },\n        {\n          \"sourceId\": \"context.release-gate\",\n          \"kind\": \"repository\",\n          \"locator\": \"path:scripts/run-v12-release-gate.mjs\",\n          \"digest\": \"sha256:552d8a11ed3f05156b935e9f461083ac9e1f00897bc797a0d3fe7c7a7d25822b\",\n          \"bytes\": 6999,\n          \"purposes\": [\n            \"Implement or verify the exact frozen V12 release-correction-r7 contract.\"\n          ],\n          \"workUnitIds\": [\n            \"fix.candidate-evidence-retention.r7\"\n          ],\n          \"readScope\": \"scripts/run-v12-release-gate.mjs\"\n        },\n        {\n          \"sourceId\": \"context.release-review-r2-harness\",\n          \"kind\": \"repository\",\n          \"locator\": \"path:docs/specs/v12-ide-run-loop/evidence/release-review-r2/run-release-review.mjs\",\n          \"digest\": \"sha256:b41e59d7cf5d905a088c7445f7ede71019be8a15aa17273fe216a60af8fc149c\",\n          \"bytes\": 66496,\n          \"purposes\": [\n            \"Implement or verify the exact frozen V12 release-correction-r7 contract.\"\n          ],\n          \"workUnitIds\": [\n            \"fix.candidate-evidence-retention.r7\"\n          ],\n          \"readScope\": \"docs/specs/v12-ide-run-loop/evidence/release-review-r2/run-release-review.mjs\"\n        },\n        {\n          \"sourceId\": \"context.release-review-r2-verifier\",\n          \"kind\": \"repository\",\n          \"locator\": \"path:docs/specs/v12-ide-run-loop/evidence/release-review-r2/verify-release-review-handoffs.mjs\",\n          \"digest\": \"sha256:e30bbf7548d6481935d14db57630e4e5bdaa9aff2df56337b957d07acc83d2aa\",\n          \"bytes\": 6984,\n          \"purposes\": [\n            \"Implement or verify the exact frozen V12 release-correction-r7 contract.\"\n          ],\n          \"workUnitIds\": [\n            \"fix.candidate-evidence-retention.r7\"\n          ],\n          \"readScope\": \"docs/specs/v12-ide-run-loop/evidence/release-review-r2/verify-release-review-handoffs.mjs\"\n        },\n        {\n          \"sourceId\": \"context.run-contract\",\n          \"kind\": \"repository\",\n          \"locator\": \"path:docs/specs/v12-ide-run-loop/evidence/implementation/release-correction-r7/inputs/specialist-run-contract.md\",\n          \"digest\": \"sha256:9b3340f0c95fc33abe945b35e3d1e0520392dee5ea01c3f78f24cb65473fa242\",\n          \"bytes\": 17133,\n          \"purposes\": [\n            \"Implement or verify the exact frozen V12 release-correction-r7 contract.\"\n          ],\n          \"workUnitIds\": [\n            \"fix.candidate-evidence-retention.r7\"\n          ],\n          \"readScope\": \"docs/specs/v12-ide-run-loop/evidence/implementation/release-correction-r7/inputs/specialist-run-contract.md\"\n        },\n        {\n          \"sourceId\": \"context.test-plan\",\n          \"kind\": \"repository\",\n          \"locator\": \"path:docs/specs/v12-ide-run-loop/evidence/implementation/release-correction-r7/inputs/test-plan.md\",\n          \"digest\": \"sha256:ffa2102cbcf6d145d4f5b0ddbc26b9b02f86433a22b4b99b9f5cb084f605d7ec\",\n          \"bytes\": 2506,\n          \"purposes\": [\n            \"Implement or verify the exact frozen V12 release-correction-r7 contract.\"\n          ],\n          \"workUnitIds\": [\n            \"fix.candidate-evidence-retention.r7\"\n          ],\n          \"readScope\": \"docs/specs/v12-ide-run-loop/evidence/implementation/release-correction-r7/inputs/test-plan.md\"\n        },\n        {\n          \"sourceId\": \"context.v12-spec\",\n          \"kind\": \"repository\",\n          \"locator\": \"path:docs/specs/v12-ide-run-loop/evidence/implementation/release-correction-r7/inputs/spec.md\",\n          \"digest\": \"sha256:b0a3610c935cacf032e9c142d9436b6f620227667c64c5bf0e296eaf4f571ab1\",\n          \"bytes\": 5478,\n          \"purposes\": [\n            \"Implement or verify the exact frozen V12 release-correction-r7 contract.\"\n          ],\n          \"workUnitIds\": [\n            \"fix.candidate-evidence-retention.r7\"\n          ],\n          \"readScope\": \"docs/specs/v12-ide-run-loop/evidence/implementation/release-correction-r7/inputs/spec.md\"\n        }\n      ],\n      \"authority\": {\n        \"requiredCapabilities\": [\n          \"fix.candidate-evidence-retention\"\n        ],\n        \"scope\": {\n          \"read\": [\n            \".gitignore\",\n            \"docs/specs/v12-ide-run-loop/evidence/implementation/release-correction-r6/approval.json\",\n            \"docs/specs/v12-ide-run-loop/evidence/implementation/release-correction-r6/handoff-verification.json\",\n            \"docs/specs/v12-ide-run-loop/evidence/implementation/release-correction-r6/handoffs/agent.4a4cca8bce6a03e1f36dfd28b9505ff33920a045636f8715b10110fdbd408985.json\",\n            \"docs/specs/v12-ide-run-loop/evidence/implementation/release-correction-r6/handoffs/agent.9579818ca2843121c26d1c38b48b0f78421bcba0ed39783ced3bfd842a45904e.json\",\n            \"docs/specs/v12-ide-run-loop/evidence/implementation/release-correction-r6/package-envelope.json\",\n            \"docs/specs/v12-ide-run-loop/evidence/implementation/release-correction-r7/inputs/adr-0005.md\",\n            \"docs/specs/v12-ide-run-loop/evidence/implementation/release-correction-r7/inputs/spec.md\",\n            \"docs/specs/v12-ide-run-loop/evidence/implementation/release-correction-r7/inputs/specialist-run-contract.md\",\n            \"docs/specs/v12-ide-run-loop/evidence/implementation/release-correction-r7/inputs/test-plan.md\",\n            \"docs/specs/v12-ide-run-loop/evidence/release-review-r2/inputs/canonical-gate-receipt.json\",\n            \"docs/specs/v12-ide-run-loop/evidence/release-review-r2/inputs/canonical-gate.stderr.log\",\n            \"docs/specs/v12-ide-run-loop/evidence/release-review-r2/inputs/canonical-gate.stdout.log\",\n            \"docs/specs/v12-ide-run-loop/evidence/release-review-r2/run-release-review.mjs\",\n            \"docs/specs/v12-ide-run-loop/evidence/release-review-r2/verify-release-review-handoffs.mjs\",\n            \"package.json\",\n            \"scripts/run-v12-release-gate.mjs\"\n          ],\n          \"write\": [\n            \".gitignore\",\n            \"docs/specs/v12-ide-run-loop/evidence/release-review-r2/run-release-review.mjs\",\n            \"scripts/run-v12-release-gate.mjs\"\n          ],\n          \"conflictZones\": [\n            \".gitignore\",\n            \"docs/specs/v12-ide-run-loop/evidence/release-review-r2/run-release-review.mjs\",\n            \"scripts/run-v12-release-gate.mjs\"\n          ]\n        },\n        \"permissions\": [\n          {\n            \"kind\": \"filesystem.read\",\n            \"scopes\": [\n              \".gitignore\",\n              \"docs/specs/v12-ide-run-loop/evidence/implementation/release-correction-r6/approval.json\",\n              \"docs/specs/v12-ide-run-loop/evidence/implementation/release-correction-r6/handoff-verification.json\",\n              \"docs/specs/v12-ide-run-loop/evidence/implementation/release-correction-r6/handoffs/agent.4a4cca8bce6a03e1f36dfd28b9505ff33920a045636f8715b10110fdbd408985.json\",\n              \"docs/specs/v12-ide-run-loop/evidence/implementation/release-correction-r6/handoffs/agent.9579818ca2843121c26d1c38b48b0f78421bcba0ed39783ced3bfd842a45904e.json\",\n              \"docs/specs/v12-ide-run-loop/evidence/implementation/release-correction-r6/package-envelope.json\",\n              \"docs/specs/v12-ide-run-loop/evidence/implementation/release-correction-r7/inputs/adr-0005.md\",\n              \"docs/specs/v12-ide-run-loop/evidence/implementation/release-correction-r7/inputs/spec.md\",\n              \"docs/specs/v12-ide-run-loop/evidence/implementation/release-correction-r7/inputs/specialist-run-contract.md\",\n              \"docs/specs/v12-ide-run-loop/evidence/implementation/release-correction-r7/inputs/test-plan.md\",\n              \"docs/specs/v12-ide-run-loop/evidence/release-review-r2/inputs/canonical-gate-receipt.json\",\n              \"docs/specs/v12-ide-run-loop/evidence/release-review-r2/inputs/canonical-gate.stderr.log\",\n              \"docs/specs/v12-ide-run-loop/evidence/release-review-r2/inputs/canonical-gate.stdout.log\",\n              \"docs/specs/v12-ide-run-loop/evidence/release-review-r2/run-release-review.mjs\",\n              \"docs/specs/v12-ide-run-loop/evidence/release-review-r2/verify-release-review-handoffs.mjs\",\n              \"package.json\",\n              \"scripts/run-v12-release-gate.mjs\"\n            ]\n          },\n          {\n            \"kind\": \"filesystem.write\",\n            \"scopes\": [\n              \".gitignore\",\n              \"docs/specs/v12-ide-run-loop/evidence/release-review-r2/run-release-review.mjs\",\n              \"scripts/run-v12-release-gate.mjs\"\n            ]\n          },\n          {\n            \"kind\": \"process.spawn\",\n            \"scopes\": [\n              \"git\",\n              \"node\",\n              \"npm\",\n              \"powershell\"\n            ]\n          }\n        ],\n        \"forbiddenEffects\": [\n          \"Do not use network access, change Git state, launch descendants, write outside the exact scope, or claim that core performs host effects.\"\n        ]\n      },\n      \"evidenceDuties\": [\n        {\n          \"criterionId\": \"criterion.fix.candidate-evidence-retention.r7\",\n          \"criterion\": \"Preserve exact canonical-gate raw evidence in Git without weakening the repository's general log-ignore policy.\",\n          \"requirementId\": \"evidence.candidate-evidence-retention.r7\",\n          \"kind\": \"review\",\n          \"duty\": \"produce\",\n          \"description\": \"Authenticate unchanged candidate-1 bytes, prove legacy and synthetic candidate-addressed canonical logs are not ignored while unrelated logs remain ignored, prove wrapper/R2 path parity and fail-closed behavior, and provide syntax, format, and focused regression results.\",\n          \"independentFromProducer\": false\n        }\n      ],\n      \"handoff\": {\n        \"destination\": \"codex.main\",\n        \"artifacts\": [\n          \"candidate-evidence-retention-correction-r7.md\"\n        ],\n        \"requiredFields\": [\n          \"apiVersion\",\n          \"kind\",\n          \"outcome\",\n          \"destination\",\n          \"goal\",\n          \"agent\",\n          \"compilationDigest\",\n          \"summary\",\n          \"workUnitsCompleted\",\n          \"artifacts\",\n          \"evidence\",\n          \"assumptions\",\n          \"risks\",\n          \"followUps\"\n        ]\n      },\n      \"stopConditions\": [\n        \"If native apply_patch fails before mutation because of the host sandbox, an exact precondition-hash-guarded PowerShell write is allowed within the declared write scope; verify the resulting file bytes immediately.\",\n        \"Return only the concrete closed SpecialistAgentHandoff JSON shape from the generated contract.\",\n        \"Run only local focused verification allowed by the contract and report every failing command truthfully.\",\n        \"Stop if any declared source is unavailable or fails its exact digest and byte binding.\",\n        \"Write only the exact declared write scope; do not change Git state, use the network, launch descendants, or widen the public contract.\"\n      ],\n      \"contentDigest\": \"sha256:374f0c75a2a31a2d0fb7aa2462c8e30573b1bd64a91909a9daf0191d95b3e5cd\"\n    }\n  ],\n  \"launchWaves\": [\n    {\n      \"start\": 0,\n      \"agentIds\": [\n        \"agent.5f16c5677b283cd8f5c13655b4b07216731fd3fdb5dfba7c6112471d5bd55c7c\"\n      ]\n    }\n  ],\n  \"contentDigest\": \"sha256:e7f6a2d27f613ea1a898b781584039dff8704d88a940965814d45b04a5537920\"\n}\n"
    },
    {
      "path": "integration.md",
      "mediaType": "text/markdown",
      "bytes": 4842,
      "digest": "sha256:7a0507dc24ef0be29b50a63a535da838c9e7a5dff3fa6942faed00708f129200",
      "content": "# Specialist Integration Contract\n\nCompilation: `sha256:e7f6a2d27f613ea1a898b781584039dff8704d88a940965814d45b04a5537920`\n\nThe integration owner launches only the contracts bound to this compilation, preserves each raw handoff, verifies required evidence, resolves declared dependencies in order, and returns to clarification or redesign when a specialist crosses its boundary.\n\n## Integration Gates\n\n1. Confirm every emitted file matches its manifest-listed raw SHA-256 digest and byte count, and every agent contract carries this compilation digest and its manifest-listed blueprint digest.\n2. Launch agents only when their dependency wave is ready and external workspace isolation is adequate.\n3. Reject undeclared files, authority, context, decisions, or evidence substitutions.\n4. Fan in handoffs through the declared integration owner; do not let one specialist silently approve its own independent duty.\n5. Run feature-level verification and review before merge, then promote only source-linked durable learning.\n\n## Compiled Plan\n\n```json\n{\n  \"compilationDigest\": \"sha256:e7f6a2d27f613ea1a898b781584039dff8704d88a940965814d45b04a5537920\",\n  \"goalId\": \"v12.ide-run-loop.implementation.release-correction\",\n  \"goalRevision\": 7,\n  \"assumptions\": [\n    {\n      \"id\": \"assumption.architecture-frozen\",\n      \"statement\": \"ADR 0005 and the Specialist Run contract are the complete implementation authority.\",\n      \"rationale\": \"Architecture fan-in passed and no blocking decision remains.\"\n    },\n    {\n      \"id\": \"assumption.candidate-one-bytes-remain-immutable\",\n      \"statement\": \"Revision 7 may make the candidate-1 raw logs visible to Git but must not change their bytes, paths, receipt bindings, or failed outcome.\",\n      \"rationale\": \"The failed attempt remains primary source evidence and cannot be rewritten to simplify retention.\"\n    },\n    {\n      \"id\": \"assumption.host-edit-fallback\",\n      \"statement\": \"After native apply_patch fails before mutation, the host may perform an exact precondition-hash-guarded PowerShell write inside the approved scope.\",\n      \"rationale\": \"Foundation Revision 1 proved the temporary worktree patch helper is unavailable while bounded escalated PowerShell writes remain auditable and fail closed.\"\n    },\n    {\n      \"id\": \"assumption.host-effects-external\",\n      \"statement\": \"All runtime, persistence, Git, merge, and memory effects remain external to core.\",\n      \"rationale\": \"V12 is a pure evidence session, not the deferred universal scheduler.\"\n    },\n    {\n      \"id\": \"assumption.raw-gate-logs-must-be-versionable\",\n      \"statement\": \"The canonical receipt is not durable release evidence unless its exact stdout and stderr source bytes can be committed and recovered from a fresh clone.\",\n      \"rationale\": \"The repository currently ignores every .log file, including both exact candidate-1 gate logs and future candidate-addressed gate logs.\"\n    }\n  ],\n  \"unresolvedDecisions\": [],\n  \"search\": {\n    \"mode\": \"exact\",\n    \"claim\": \"exhaustive_partition_search_fixed_scheduler\",\n    \"workUnitCount\": 1,\n    \"evaluatedCandidates\": 1,\n    \"eligibleCandidates\": 1,\n    \"retainedAlternatives\": 0,\n    \"evaluationSetDigest\": \"sha256:2e0b8eb5d4b9f9df75b71e3419222e94574d904823f6154d2626c5839705fe2f\"\n  },\n  \"selectedCandidateId\": \"team.95637f6ac2bb74c533055e0666c20a7824db48103f5998e8831bdfedc23284e9\",\n  \"selectedMetrics\": {\n    \"agentCount\": 1,\n    \"projectedMakespan\": 6,\n    \"peakConcurrency\": 1,\n    \"conflictPairs\": 0,\n    \"handoffCount\": 0,\n    \"duplicatedContextBytes\": 0,\n    \"duplicatedPermissionScopes\": 0,\n    \"totalWorkWeight\": 5,\n    \"totalStartupCost\": 1,\n    \"totalHandoffCost\": 0\n  },\n  \"selectionReason\": {\n    \"kind\": \"serial_selected\",\n    \"decisiveField\": \"serial_baseline\",\n    \"selectedValue\": \"team.95637f6ac2bb74c533055e0666c20a7824db48103f5998e8831bdfedc23284e9\",\n    \"serialValue\": \"team.95637f6ac2bb74c533055e0666c20a7824db48103f5998e8831bdfedc23284e9\",\n    \"serialRejectionCodes\": []\n  },\n  \"serialBaseline\": {\n    \"id\": \"team.95637f6ac2bb74c533055e0666c20a7824db48103f5998e8831bdfedc23284e9\",\n    \"eligible\": true,\n    \"rejectionCodes\": [],\n    \"metrics\": {\n      \"agentCount\": 1,\n      \"projectedMakespan\": 6,\n      \"peakConcurrency\": 1,\n      \"conflictPairs\": 0,\n      \"handoffCount\": 0,\n      \"duplicatedContextBytes\": 0,\n      \"duplicatedPermissionScopes\": 0,\n      \"totalWorkWeight\": 5,\n      \"totalStartupCost\": 1,\n      \"totalHandoffCost\": 0\n    }\n  },\n  \"launchWaves\": [\n    {\n      \"start\": 0,\n      \"agentIds\": [\n        \"agent.5f16c5677b283cd8f5c13655b4b07216731fd3fdb5dfba7c6112471d5bd55c7c\"\n      ]\n    }\n  ],\n  \"blueprintDigests\": [\n    {\n      \"agentId\": \"agent.5f16c5677b283cd8f5c13655b4b07216731fd3fdb5dfba7c6112471d5bd55c7c\",\n      \"digest\": \"sha256:374f0c75a2a31a2d0fb7aa2462c8e30573b1bd64a91909a9daf0191d95b3e5cd\"\n    }\n  ]\n}\n```\n"
    },
    {
      "path": "manifest.json",
      "mediaType": "application/json",
      "bytes": 1503,
      "digest": "sha256:d2d53c17a5da4050caa362c65dfefdd19fd1eabfca79289b2cdaec9e1b42b2ef",
      "content": "{\n  \"apiVersion\": \"swecircuit/specialist/v1alpha1\",\n  \"kind\": \"SpecialistPackageManifest\",\n  \"goalId\": \"v12.ide-run-loop.implementation.release-correction\",\n  \"goalRevision\": 7,\n  \"fileDigestAlgorithm\": \"sha256\",\n  \"fileDigestScope\": \"raw-file-bytes\",\n  \"compilationDigest\": \"sha256:e7f6a2d27f613ea1a898b781584039dff8704d88a940965814d45b04a5537920\",\n  \"selectedCandidateId\": \"team.95637f6ac2bb74c533055e0666c20a7824db48103f5998e8831bdfedc23284e9\",\n  \"launchWaves\": [\n    {\n      \"start\": 0,\n      \"agentIds\": [\n        \"agent.5f16c5677b283cd8f5c13655b4b07216731fd3fdb5dfba7c6112471d5bd55c7c\"\n      ]\n    }\n  ],\n  \"compilationFile\": \"compilation.json\",\n  \"compilationFileDigest\": \"sha256:6832e04cad3f2d06a63538a3a4d9a57a3db7119337acbfdfceb648e667c9fac8\",\n  \"compilationFileBytes\": 61610,\n  \"agents\": [\n    {\n      \"agentId\": \"agent.5f16c5677b283cd8f5c13655b4b07216731fd3fdb5dfba7c6112471d5bd55c7c\",\n      \"blueprintDigest\": \"sha256:374f0c75a2a31a2d0fb7aa2462c8e30573b1bd64a91909a9daf0191d95b3e5cd\",\n      \"contractFile\": \"agents/agent.5f16c5677b283cd8f5c13655b4b07216731fd3fdb5dfba7c6112471d5bd55c7c.md\",\n      \"contractDigest\": \"sha256:277b71bd417898146b4e60283b0728ee91cec1ece58a72e4a29f5993b40b717d\",\n      \"contractBytes\": 21651\n    }\n  ],\n  \"integrationFile\": \"integration.md\",\n  \"integrationDigest\": \"sha256:7a0507dc24ef0be29b50a63a535da838c9e7a5dff3fa6942faed00708f129200\",\n  \"integrationBytes\": 4842,\n  \"contentDigest\": \"sha256:8ceab3582d8d2cb0cdfffd640cd0f958739cbf27723c33898eb04ca1c29776f4\"\n}\n"
    }
  ]
}
